Workbook
Name UPDATE: 'Data Sheet'!$E$1

Sheet Profit & Loss
A1: ='Data Sheet'!B1 -> SUN PHARMACEUTICAL INDUSTRIES LTD | H1: =UPDATE -> SUN PHARMACEUTICAL INDUSTRIES LTD | M1: SCREENER.IN
A3: Narration | B3: ='Data Sheet'!B16 -> 42825 | C3: ='Data Sheet'!C16 -> 43190 | D3: ='Data Sheet'!D16 -> 43555 | E3: ='Data Sheet'!E16 -> 43921 | F3: ='Data Sheet'!F16 -> 44286 | G3: ='Data Sheet'!G16 -> 44651 | H3: ='Data Sheet'!H16 -> 45016 | I3: ='Data Sheet'!I16 -> 45382 | ... K3: ='Data Sheet'!K16 -> 46112 | L3: Trailing | M3: Best Case | N3: Worst Case
A4: Sales | B4: ='Data Sheet'!B17 -> 31578.44 | C4: ='Data Sheet'!C17 -> 26489.46 | D4: ='Data Sheet'!D17 -> 29065.91 | E4: ='Data Sheet'!E17 -> 32837.5 | F4: ='Data Sheet'!F17 -> 33498.14 | G4: ='Data Sheet'!G17 -> 38654.49 | H4: ='Data Sheet'!H17 -> 43885.68 | I4: ='Data Sheet'!I17 -> 48496.85 | ... K4: ='Data Sheet'!K17 -> 58462.04 | L4: =SUM('Data Sheet'!H42:K42) -> 58462.04 | M4: =$K4+M23*K4 -> 65004.023 | N4: =$K4+N23*L4 -> 62602.883
A5: Expenses | B5: =SUM('Data Sheet'!B18,'Data Sheet'!B20:B24, -1*'Data Sheet'!B19) -> 21476.42 | C5: =SUM('Data Sheet'!C18,'Data Sheet'!C20:C24, -1*'Data Sheet'!C19) -> 20858.04 | D5: =SUM('Data Sheet'!D18,'Data Sheet'!D20:D24, -1*'Data Sheet'!D19) -> 22688.93 | E5: =SUM('Data Sheet'!E18,'Data Sheet'!E20:E24, -1*'Data Sheet'!E19) -> 25854.66 | F5: =SUM('Data Sheet'!F18,'Data Sheet'!F20:F24, -1*'Data Sheet'!F19) -> 25028.18 | G5: =SUM('Data Sheet'!G18,'Data Sheet'!G20:G24, -1*'Data Sheet'!G19) -> 28396.92 | H5: =SUM('Data Sheet'!H18,'Data Sheet'!H20:H24, -1*'Data Sheet'!H19) -> 32235.24 | I5: =SUM('Data Sheet'!I18,'Data Sheet'!I20:I24, -1*'Data Sheet'!I19) -> 35479.08 | ... K5: =SUM('Data Sheet'!K18,'Data Sheet'!K20:K24, -1*'Data Sheet'!K19) -> 40730.64 | L5: =SUM('Data Sheet'!H43:K43) -> 40730.64 | M5: =M4-M6 -> 45288.455 | N5: =N4-N6 -> 45931.623
A6: Operating Profit | B6: =B4-B5 -> 10102.02 | C6: =C4-C5 -> 5631.42 | D6: =D4-D5 -> 6376.98 | E6: =E4-E5 -> 6982.84 | F6: =F4-F5 -> 8469.96 | G6: =G4-G5 -> 10257.57 | H6: =H4-H5 -> 11650.44 | I6: =I4-I5 -> 13017.77 | ... K6: =K4-K5 -> 17731.4 | L6: =SUM('Data Sheet'!H50:K50) -> 17731.4 | M6: =M4*M24 -> 19715.568 | N6: =N4*N24 -> 16671.26
A7: Other Income | B7: ='Data Sheet'!B25 -> 610.4 | C7: ='Data Sheet'!C25 -> -135.03 | D7: ='Data Sheet'!D25 -> -258.28 | E7: ='Data Sheet'!E25 -> 382.26 | F7: ='Data Sheet'!F25 -> -3449.21 | G7: ='Data Sheet'!G25 -> -3505.16 | H7: ='Data Sheet'!H25 -> 459.42 | I7: ='Data Sheet'!I25 -> 865.23 | ... K7: ='Data Sheet'!K25 -> 664.24 | L7: =SUM(#REF!) -> #REF! | M7: 0 | N7: 0
A8: Depreciation | B8: ='Data Sheet'!B26 -> 1264.75 | C8: ='Data Sheet'!C26 -> 1499.84 | D8: ='Data Sheet'!D26 -> 1753.25 | E8: ='Data Sheet'!E26 -> 2052.78 | F8: ='Data Sheet'!F26 -> 2079.95 | G8: ='Data Sheet'!G26 -> 2143.74 | H8: ='Data Sheet'!H26 -> 2529.43 | I8: ='Data Sheet'!I26 -> 2556.64 | ... K8: ='Data Sheet'!K26 -> 2937.85 | L8: =SUM(#REF!) -> #REF! | M8: =+$L8 -> #REF! | N8: =+$L8 -> #REF!
A9: Interest | B9: ='Data Sheet'!B27 -> 399.8 | C9: ='Data Sheet'!C27 -> 517.57 | D9: ='Data Sheet'!D27 -> 555.25 | E9: ='Data Sheet'!E27 -> 302.73 | F9: ='Data Sheet'!F27 -> 141.43 | G9: ='Data Sheet'!G27 -> 127.35 | H9: ='Data Sheet'!H27 -> 172 | I9: ='Data Sheet'!I27 -> 238.47 | ... K9: ='Data Sheet'!K27 -> 338.91 | L9: =SUM(#REF!) -> #REF! | M9: =+$L9 -> #REF! | N9: =+$L9 -> #REF!
A10: Profit before tax | B10: ='Data Sheet'!B28 -> 9047.87 | C10: ='Data Sheet'!C28 -> 3478.98 | D10: ='Data Sheet'!D28 -> 3810.2 | E10: ='Data Sheet'!E28 -> 5009.59 | F10: ='Data Sheet'!F28 -> 2799.37 | G10: ='Data Sheet'!G28 -> 4481.32 | H10: ='Data Sheet'!H28 -> 9408.43 | I10: ='Data Sheet'!I28 -> 11087.89 | ... K10: ='Data Sheet'!K28 -> 15118.88 | L10: =SUM(#REF!) -> #REF! | M10: =M6+M7-SUM(M8:M9) -> #REF! | N10: =N6+N7-SUM(N8:N9) -> #REF!
A11: Tax | B11: ='Data Sheet'!B29 -> 1211.57 | C11: ='Data Sheet'!C29 -> 911.04 | D11: ='Data Sheet'!D29 -> 600.88 | E11: ='Data Sheet'!E29 -> 822.8 | F11: ='Data Sheet'!F29 -> 514.69 | G11: ='Data Sheet'!G29 -> 1075.5 | H11: ='Data Sheet'!H29 -> 847.59 | I11: ='Data Sheet'!I29 -> 1439.45 | ... K11: ='Data Sheet'!K29 -> 3554.36 | L11: =SUM(#REF!) -> #REF! | M11: =IF($L10>0,$L11/$L10,0) -> #REF! | N11: =IF($L10>0,$L11/$L10,0) -> #REF!
A12: Net profit | B12: ='Data Sheet'!B30 -> 6964.37 | C12: ='Data Sheet'!C30 -> 2095.7 | D12: ='Data Sheet'!D30 -> 2665.42 | E12: ='Data Sheet'!E30 -> 3764.93 | F12: ='Data Sheet'!F30 -> 2903.82 | G12: ='Data Sheet'!G30 -> 3272.73 | H12: ='Data Sheet'!H30 -> 8473.58 | I12: ='Data Sheet'!I30 -> 9576.38 | ... K12: ='Data Sheet'!K30 -> 11479.42 | L12: =SUM(#REF!) -> #REF! | M12: =M10-M11*M10 -> #REF! | N12: =N10-N11*N10 -> #REF!
A13: EPS | B13: =IF('Data Sheet'!B93>0,B12/'Data Sheet'!B93,0) -> 29.026674 | C13: =IF('Data Sheet'!C93>0,C12/'Data Sheet'!C93,0) -> 8.7346309 | D13: =IF('Data Sheet'!D93>0,D12/'Data Sheet'!D93,0) -> 11.109157 | E13: =IF('Data Sheet'!E93>0,E12/'Data Sheet'!E93,0) -> 15.691785 | F13: =IF('Data Sheet'!F93>0,F12/'Data Sheet'!F93,0) -> 12.10278 | G13: =IF('Data Sheet'!G93>0,G12/'Data Sheet'!G93,0) -> 13.640353 | H13: =IF('Data Sheet'!H93>0,H12/'Data Sheet'!H93,0) -> 35.316884 | I13: =IF('Data Sheet'!I93>0,I12/'Data Sheet'!I93,0) -> 39.913225 | ... K13: =IF('Data Sheet'!K93>0,K12/'Data Sheet'!K93,0) -> 47.844871 | L13: =IF('Data Sheet'!$B6>0,'Profit & Loss'!L12/'Data Sheet'!$B6,0) -> #REF! | M13: =IF('Data Sheet'!$B6>0,'Profit & Loss'!M12/'Data Sheet'!$B6,0) -> #REF! | N13: =IF('Data Sheet'!$B6>0,'Profit & Loss'!N12/'Data Sheet'!$B6,0) -> #REF!
A14: Price to earning | B14: =IF(B15>0,B15/B13,"") -> 23.707504 | C14: =IF(C15>0,C15/C13,"") -> 56.682418 | D14: =IF(D15>0,D15/D13,"") -> 43.104081 | E14: =IF(E15>0,E15/E13,"") -> 22.451238 | F14: =IF(F15>0,F15/F13,"") -> 49.39361 | G14: =IF(G15>0,G15/G13,"") -> 67.062045 | H14: =IF(H15>0,H15/H13,"") -> 27.836544 | I14: =IF(I15>0,I15/I13,"") -> 40.601831 | ... K14: =IF(K15>0,K15/K13,"") -> 36.727029 | L14: =IF(L13>0,L15/L13,0) -> #REF! | M14: =M25 -> #REF! | N14: =N25 -> #REF!
A15: Price | B15: ='Data Sheet'!B90 -> 688.15 | C15: ='Data Sheet'!C90 -> 495.1 | D15: ='Data Sheet'!D90 -> 478.85 | E15: ='Data Sheet'!E90 -> 352.3 | F15: ='Data Sheet'!F90 -> 597.8 | G15: ='Data Sheet'!G90 -> 914.75 | H15: ='Data Sheet'!H90 -> 983.1 | I15: ='Data Sheet'!I90 -> 1620.55 | ... K15: ='Data Sheet'!K90 -> 1757.2 | L15: ='Data Sheet'!B8 -> 1789.65 | M15: =M13*M14 -> #REF! | N15: =N13*N14 -> #REF!
A17: RATIOS:
A18: Dividend Payout | B18: =IF('Data Sheet'!B30>0, 'Data Sheet'!B31/'Data Sheet'!B30, 0) -> 0.12057946 | C18: =IF('Data Sheet'!C30>0, 'Data Sheet'!C31/'Data Sheet'!C30, 0) -> 0.22897361 | D18: =IF('Data Sheet'!D30>0, 'Data Sheet'!D31/'Data Sheet'!D30, 0) -> 0.24754448 | E18: =IF('Data Sheet'!E30>0, 'Data Sheet'!E31/'Data Sheet'!E30, 0) -> 0.25491045 | F18: =IF('Data Sheet'!F30>0, 'Data Sheet'!F31/'Data Sheet'!F30, 0) -> 0.61969406 | G18: =IF('Data Sheet'!G30>0, 'Data Sheet'!G31/'Data Sheet'!G30, 0) -> 0.73311883 | H18: =IF('Data Sheet'!H30>0, 'Data Sheet'!H31/'Data Sheet'!H30, 0) -> 0.32562388 | I18: =IF('Data Sheet'!I30>0, 'Data Sheet'!I31/'Data Sheet'!I30, 0) -> 0.33823428 | ... K18: =IF('Data Sheet'!K30>0, 'Data Sheet'!K31/'Data Sheet'!K30, 0) -> 0.33441411
A19: OPM | B19: =IF(B6>0,B6/B4,0) -> 0.31990244 | C19: =IF(C6>0,C6/C4,0) -> 0.21259097 | D19: =IF(D6>0,D6/D4,0) -> 0.21939723 | E19: =IF(E6>0,E6/E4,0) -> 0.21264834 | F19: =IF(F6>0,F6/F4,0) -> 0.25284867 | G19: =IF(G6>0,G6/G4,0) -> 0.26536555 | H19: =IF(H6>0,H6/H4,0) -> 0.26547247 | I19: =IF(I6>0,I6/I4,0) -> 0.26842506 | ... L19: =IF(L6>0,L6/L4,0) -> 0.30329766
G22: TRENDS: | H22: 10 YEARS | I22: 7 YEARS | J22: 5 YEARS | K22: 3 YEARS | L22: RECENT | M22: BEST | N22: WORST
G23: Sales Growth | H23: =IF(B4=0,"",POWER($K4/B4,1/9)-1) -> 0.070829596 | I23: =IF(D4=0,"",POWER($K4/D4,1/7)-1) -> 0.10498331 | J23: =IF(F4=0,"",POWER($K4/F4,1/5)-1) -> 0.11781686 | K23: =IF(H4=0,"",POWER($K4/H4, 1/3)-1) -> 0.10031503 | L23: =IF(ISERROR(MAX(IF(J4=0,"",(K4-J4)/J4),IF(K4=0,"",(L4-K4)/K4))),"",MAX(IF(J4=0,"",(K4-J4)/J4),IF(K4=0,"",(L4-K4)/K4))) -> 0.11190138 | M23: =MAX(K23:L23) -> 0.11190138 | N23: =MIN(H23:L23) -> 0.070829596
G24: OPM | H24: =IF(SUM(B4:$K$4)=0,"",SUMPRODUCT(B19:$K$19,B4:$K$4)/SUM(B4:$K$4)) -> 0.26630179 | I24: =IF(SUM(E4:$K$4)=0,"",SUMPRODUCT(E19:$K$19,E4:$K$4)/SUM(E4:$K$4)) -> 0.26984726 | J24: =IF(SUM(G4:$K$4)=0,"",SUMPRODUCT(G19:$K$19,G4:$K$4)/SUM(G4:$K$4)) -> 0.27995844 | K24: =IF(SUM(I4:$K$4)=0, "", SUMPRODUCT(I19:$K$19,I4:$K$4)/SUM(I4:$K$4)) -> 0.28747899 | L24: =L19 -> 0.30329766 | M24: =MAX(K24:L24) -> 0.30329766 | N24: =MIN(H24:L24) -> 0.26630179
G25: Price to Earning | H25: =IF(ISERROR(AVERAGEIF(B14:$L14,">0")),"",AVERAGEIF(B14:$L14,">0")) -> 40.564893 | I25: =IF(ISERROR(AVERAGEIF(E14:$L14,">0")),"",AVERAGEIF(E14:$L14,">0")) -> 40.307847 | J25: =IF(ISERROR(AVERAGEIF(G14:$L14,">0")),"",AVERAGEIF(G14:$L14,">0")) -> 42.062016 | K25: =IF(ISERROR(AVERAGEIF(I14:$L14,">0")),"",AVERAGEIF(I14:$L14,">0")) -> 38.470496 | L25: =L14 -> #REF! | M25: =MAX(K25:L25) -> #REF! | N25: =MIN(H25:L25) -> #REF!

Sheet HistoricalFS
B2: ="Historical Financial Statement - "&UPDATE -> Historical Financial Statement - SUN PHARMACEUTICAL INDUSTRIES LTD
B3: Years | C3: ='Data Sheet'!B16 -> 42825 | D3: ='Data Sheet'!C16 -> 43190 | E3: ='Data Sheet'!D16 -> 43555 | F3: ='Data Sheet'!E16 -> 43921 | G3: ='Data Sheet'!F16 -> 44286 | H3: ='Data Sheet'!G16 -> 44651 | I3: ='Data Sheet'!H16 -> 45016 | J3: ='Data Sheet'!I16 -> 45382 | ... L3: ='Data Sheet'!K16 -> 46112 | M3: LTM
A5: # | B5: Income Statement
B6: Sales | C6: =IFERROR('Data Sheet'!B17,0) -> 31578.44 | D6: =IFERROR('Data Sheet'!C17,0) -> 26489.46 | E6: =IFERROR('Data Sheet'!D17,0) -> 29065.91 | F6: =IFERROR('Data Sheet'!E17,0) -> 32837.5 | G6: =IFERROR('Data Sheet'!F17,0) -> 33498.14 | H6: =IFERROR('Data Sheet'!G17,0) -> 38654.49 | I6: =IFERROR('Data Sheet'!H17,0) -> 43885.68 | J6: =IFERROR('Data Sheet'!I17,0) -> 48496.85 | ... L6: =IFERROR('Data Sheet'!K17,0) -> 58462.04 | M6: =IFERROR(SUM('Data Sheet'!H42:K42),0) -> 58462.04
B7: Sales Growth | C7: - | D7: =D6/C6-1 -> -0.16115362 | E7: =E6/D6-1 -> 0.097263213 | F7: =F6/E6-1 -> 0.12975991 | G7: =G6/F6-1 -> 0.020118462 | H7: =H6/G6-1 -> 0.15392944 | I7: =I6/H6-1 -> 0.13533201 | J7: =J6/I6-1 -> 0.10507232 | K7: =K6/J6-1 -> 0.084161961 | ... M7: =M6/L6-1 -> 0
B9: COGS | C9: =IFERROR(SUM('Data Sheet'!B18,'Data Sheet'!B20:B22)-1*'Data Sheet'!B19,0) -> 15531.59 | D9: =IFERROR(SUM('Data Sheet'!C18,'Data Sheet'!C20:C22)-1*'Data Sheet'!C19,0) -> 15180.05 | E9: =IFERROR(SUM('Data Sheet'!D18,'Data Sheet'!D20:D22)-1*'Data Sheet'!D19,0) -> 16334.37 | F9: =IFERROR(SUM('Data Sheet'!E18,'Data Sheet'!E20:E22)-1*'Data Sheet'!E19,0) -> 17904.69 | G9: =IFERROR(SUM('Data Sheet'!F18,'Data Sheet'!F20:F22)-1*'Data Sheet'!F19,0) -> 17903.18 | H9: =IFERROR(SUM('Data Sheet'!G18,'Data Sheet'!G20:G22)-1*'Data Sheet'!G19,0) -> 20235.86 | I9: =IFERROR(SUM('Data Sheet'!H18,'Data Sheet'!H20:H22)-1*'Data Sheet'!H19,0) -> 21725.01 | J9: =IFERROR(SUM('Data Sheet'!I18,'Data Sheet'!I20:I22)-1*'Data Sheet'!I19,0) -> 23039.07 | ... L9: =IFERROR(SUM('Data Sheet'!K18,'Data Sheet'!K20:K22)-1*'Data Sheet'!K19,0) -> 22962.54 | M9: =IFERROR(SUM('Data Sheet'!H43:K43),0) -> 40730.64
B10: COGS % Sales | C10: =C9/C6 -> 0.49184159 | D10: =D9/D6 -> 0.57306 | E10: =E9/E6 -> 0.5619769 | F10: =F9/F6 -> 0.54525131 | G10: =G9/G6 -> 0.53445296 | H10: =H9/H6 -> 0.52350607 | I10: =I9/I6 -> 0.49503642 | J10: =J9/J6 -> 0.47506323 | ... M10: =M9/M6 -> 0.69670234
B12: Gross Profit | C12: =C6-C9 -> 16046.85 | D12: =D6-D9 -> 11309.41 | E12: =E6-E9 -> 12731.54 | F12: =F6-F9 -> 14932.81 | G12: =G6-G9 -> 15594.96 | H12: =H6-H9 -> 18418.63 | I12: =I6-I9 -> 22160.67 | J12: =J6-J9 -> 25457.78 | ... M12: =M6-M9 -> 17731.4
B13: Gross Margin | C13: =C12/C6 -> 0.50815841 | D13: =D12/D6 -> 0.42694 | E13: =E12/E6 -> 0.4380231 | F13: =F12/F6 -> 0.45474869 | G13: =G12/G6 -> 0.46554704 | H13: =H12/H6 -> 0.47649393 | I13: =I12/I6 -> 0.50496358 | J13: =J12/J6 -> 0.52493677 | ... M13: =M12/M6 -> 0.30329766
B15: Selling & Gen Exp | C15: =IFERROR(SUM('Data Sheet'!B23:B24),0) -> 5944.83 | D15: =IFERROR(SUM('Data Sheet'!C23:C24),0) -> 5677.99 | E15: =IFERROR(SUM('Data Sheet'!D23:D24),0) -> 6354.56 | F15: =IFERROR(SUM('Data Sheet'!E23:E24),0) -> 7949.97 | G15: =IFERROR(SUM('Data Sheet'!F23:F24),0) -> 7125 | H15: =IFERROR(SUM('Data Sheet'!G23:G24),0) -> 8161.06 | I15: =IFERROR(SUM('Data Sheet'!H23:H24),0) -> 10510.23 | J15: =IFERROR(SUM('Data Sheet'!I23:I24),0) -> 12440.01 | ... L15: =IFERROR(SUM('Data Sheet'!K23:K24),0) -> 17768.1 | M15: 0
B16: S&G Exp % Sales | C16: =C15/C6 -> 0.18825597 | D16: =D15/D6 -> 0.21434903 | E16: =E15/E6 -> 0.21862587 | F16: =F15/F6 -> 0.24210034 | G16: =G15/G6 -> 0.21269838 | H16: =H15/H6 -> 0.21112838 | I16: =I15/I6 -> 0.23949111 | J16: =J15/J6 -> 0.25651171 | ... L16: =L15/L6 -> 0.30392542 | M16: 0
B18: EBITDA | C18: =C12-C15 -> 10102.02 | D18: =D12-D15 -> 5631.42 | E18: =E12-E15 -> 6376.98 | F18: =F12-F15 -> 6982.84 | G18: =G12-G15 -> 8469.96 | H18: =H12-H15 -> 10257.57 | I18: =I12-I15 -> 11650.44 | J18: =J12-J15 -> 13017.77 | ... M18: =M12-M15 -> 17731.4
B19: EBITDA Margins | C19: =C18/C6 -> 0.31990244 | D19: =D18/D6 -> 0.21259097 | E19: =E18/E6 -> 0.21939723 | F19: =F18/F6 -> 0.21264834 | G19: =G18/G6 -> 0.25284867 | H19: =H18/H6 -> 0.26536555 | I19: =I18/I6 -> 0.26547247 | J19: =J18/J6 -> 0.26842506 | ... M19: =M18/M6 -> 0.30329766
B21: Other income | C21: =IFERROR('Data Sheet'!B25,0) -> 610.4 | D21: =IFERROR('Data Sheet'!C25,0) -> -135.03 | E21: =IFERROR('Data Sheet'!D25,0) -> -258.28 | F21: =IFERROR('Data Sheet'!E25,0) -> 382.26 | G21: =IFERROR('Data Sheet'!F25,0) -> -3449.21 | H21: =IFERROR('Data Sheet'!G25,0) -> -3505.16 | I21: =IFERROR('Data Sheet'!H25,0) -> 459.42 | J21: =IFERROR('Data Sheet'!I25,0) -> 865.23 | ... M21: =IFERROR('Data Sheet'!L25,0) -> 0
B23: Interest | C23: =IFERROR('Data Sheet'!B27,0) -> 399.8 | D23: =IFERROR('Data Sheet'!C27,0) -> 517.57 | E23: =IFERROR('Data Sheet'!D27,0) -> 555.25 | F23: =IFERROR('Data Sheet'!E27,0) -> 302.73 | G23: =IFERROR('Data Sheet'!F27,0) -> 141.43 | H23: =IFERROR('Data Sheet'!G27,0) -> 127.35 | I23: =IFERROR('Data Sheet'!H27,0) -> 172 | J23: =IFERROR('Data Sheet'!I27,0) -> 238.47 | ... L23: =IFERROR('Data Sheet'!K27,0) -> 338.91 | M23: =IFERROR(SUM('Data Sheet'!H46:K46),0) -> 338.91
B24: Interest % Sales | C24: =C23/C6 -> 0.012660537 | D24: =D23/D6 -> 0.019538715 | E24: =E23/E6 -> 0.019103135 | F24: =F23/F6 -> 0.0092190331 | G24: =G23/G6 -> 0.0042220255 | H24: =H23/H6 -> 0.003294572 | I24: =I23/I6 -> 0.0039192739 | J24: =J23/J6 -> 0.0049172266 | ... M24: =M23/M6 -> 0.005797095
P25: Other Income | Q25: =IFERROR('Data Sheet'!B25,0) -> 610.4 | R25: =IFERROR('Data Sheet'!C25,0) -> -135.03 | S25: =IFERROR('Data Sheet'!D25,0) -> -258.28 | T25: =IFERROR('Data Sheet'!E25,0) -> 382.26 | U25: =IFERROR('Data Sheet'!F25,0) -> -3449.21 | V25: =IFERROR('Data Sheet'!G25,0) -> -3505.16 | W25: =IFERROR('Data Sheet'!H25,0) -> 459.42 | X25: =IFERROR('Data Sheet'!I25,0) -> 865.23 | ... Z25: =IFERROR('Data Sheet'!K25,0) -> 664.24 | AA25: =IFERROR(SUM('Data Sheet'!H44:K44),0) -> 664.24
B26: Depreciation | C26: =IFERROR('Data Sheet'!B26,0) -> 1264.75 | D26: =IFERROR('Data Sheet'!C26,0) -> 1499.84 | E26: =IFERROR('Data Sheet'!D26,0) -> 1753.25 | F26: =IFERROR('Data Sheet'!E26,0) -> 2052.78 | G26: =IFERROR('Data Sheet'!F26,0) -> 2079.95 | H26: =IFERROR('Data Sheet'!G26,0) -> 2143.74 | I26: =IFERROR('Data Sheet'!H26,0) -> 2529.43 | J26: =IFERROR('Data Sheet'!I26,0) -> 2556.64 | ... L26: =IFERROR('Data Sheet'!K26,0) -> 2937.85 | M26: 0
B27: Depreciation % Sales | C27: =C26/C6 -> 0.04005106 | D27: =D26/D6 -> 0.056620256 | E27: =E26/E6 -> 0.060319804 | F27: =F26/F6 -> 0.062513285 | G27: =G26/G6 -> 0.062091507 | H27: =H26/H6 -> 0.055459017 | I27: =I26/I6 -> 0.057636796 | J27: =J26/J6 -> 0.052717651 | ... M27: =M26/M6 -> 0
B29: EBIT | C29: =C18-C26 -> 8837.27 | D29: =D18-D26 -> 4131.58 | E29: =E18-E26 -> 4623.73 | F29: =F18-F26 -> 4930.06 | G29: =G18-G26 -> 6390.01 | H29: =H18-H26 -> 8113.83 | I29: =I18-I26 -> 9121.01 | J29: =J18-J26 -> 10461.13 | ... M29: =M18-M26 -> 17731.4
B30: EBIT % Sales | C30: =C29/C6 -> 0.27985138 | D30: =D29/D6 -> 0.15597071 | E30: =E29/E6 -> 0.15907742 | F30: =F29/F6 -> 0.15013506 | G30: =G29/G6 -> 0.19075716 | H30: =H29/H6 -> 0.20990653 | I30: =I29/I6 -> 0.20783568 | J30: =J29/J6 -> 0.21570741 | ... M30: =M29/M6 -> 0.30329766
B32: Earnings Before Tax | C32: =C18-C23-C26+C21 -> 9047.87 | D32: =D18-D23-D26+D21 -> 3478.98 | E32: =E18-E23-E26+E21 -> 3810.2 | F32: =F18-F23-F26+F21 -> 5009.59 | G32: =G18-G23-G26+G21 -> 2799.37 | H32: =H18-H23-H26+H21 -> 4481.32 | I32: =I18-I23-I26+I21 -> 9408.43 | J32: =J18-J23-J26+J21 -> 11087.89 | ... M32: =M18-M23-M26+M21 -> 17392.49
B33: EBT % Sales | C33: =C32/C6 -> 0.28652049 | D33: =D32/D6 -> 0.1313345 | E33: =E32/E6 -> 0.13108827 | F33: =F32/F6 -> 0.15255699 | G33: =G32/G6 -> 0.083567923 | H33: =H32/H6 -> 0.11593272 | I33: =I32/I6 -> 0.21438497 | J33: =J32/J6 -> 0.22863114 | ... M33: =M32/M6 -> 0.29750057
B35: Tax | C35: =IFERROR('Data Sheet'!B29,0) -> 1211.57 | D35: =IFERROR('Data Sheet'!C29,0) -> 911.04 | E35: =IFERROR('Data Sheet'!D29,0) -> 600.88 | F35: =IFERROR('Data Sheet'!E29,0) -> 822.8 | G35: =IFERROR('Data Sheet'!F29,0) -> 514.69 | H35: =IFERROR('Data Sheet'!G29,0) -> 1075.5 | I35: =IFERROR('Data Sheet'!H29,0) -> 847.59 | J35: =IFERROR('Data Sheet'!I29,0) -> 1439.45 | ... L35: =IFERROR('Data Sheet'!K29,0) -> 3554.36 | M35: =IFERROR(SUM('Data Sheet'!H48:K48),0) -> 3554.36
B36: Effective Tax Rate | C36: =C35/C32 -> 0.13390665 | D36: =D35/D32 -> 0.26186986 | E36: =E35/E32 -> 0.15770301 | F36: =F35/F32 -> 0.16424498 | G36: =G35/G32 -> 0.18385923 | H36: =H35/H32 -> 0.23999625 | I36: =I35/I32 -> 0.090088357 | J36: =J35/J32 -> 0.12982181 | ... M36: =M35/M32 -> 0.20436177
B38: Net Profit | C38: =C32-C35 -> 7836.3 | D38: =D32-D35 -> 2567.94 | E38: =E32-E35 -> 3209.32 | F38: =F32-F35 -> 4186.79 | G38: =G32-G35 -> 2284.68 | H38: =H32-H35 -> 3405.82 | I38: =I32-I35 -> 8560.84 | J38: =J32-J35 -> 9648.44 | ... M38: =M32-M35 -> 13838.13
B39: Net Margin | C39: =C38/C6 -> 0.24815349 | D39: =D38/D6 -> 0.096941954 | E39: =E38/E6 -> 0.11041526 | F39: =F38/F6 -> 0.12750027 | G39: =G38/G6 -> 0.06820319 | H39: =H38/H6 -> 0.088109299 | I39: =I38/I6 -> 0.19507138 | J39: =J38/J6 -> 0.19894983 | ... M39: =M38/M6 -> 0.23670282
B41: No. of Equity Shares | C41: =IFERROR('Data Sheet'!B93,0) -> 239.93 | D41: =IFERROR('Data Sheet'!C93,0) -> 239.93 | E41: =IFERROR('Data Sheet'!D93,0) -> 239.93 | F41: =IFERROR('Data Sheet'!E93,0) -> 239.93 | G41: =IFERROR('Data Sheet'!F93,0) -> 239.93 | H41: =IFERROR('Data Sheet'!G93,0) -> 239.93 | I41: =IFERROR('Data Sheet'!H93,0) -> 239.93 | J41: =IFERROR('Data Sheet'!I93,0) -> 239.93 | ... L41: =IFERROR('Data Sheet'!K93,0) -> 239.93 | M41: =IFERROR('Data Sheet'!K93,0) -> 239.93
B43: EPS | C43: =IFERROR(C38/C41,0) -> 32.660776 | D43: =IFERROR(D38/D41,0) -> 10.702872 | E43: =IFERROR(E38/E41,0) -> 13.376068 | F43: =IFERROR(F38/F41,0) -> 17.450048 | G43: =IFERROR(G38/G41,0) -> 9.5222773 | H43: =IFERROR(H38/H41,0) -> 14.195057 | I43: =IFERROR(I38/I41,0) -> 35.680574 | J43: =IFERROR(J38/J41,0) -> 40.213562 | ... M43: =IFERROR(M38/M41,0) -> 57.675697
B44: EPS Growth % | D44: =IFERROR(D43/C43-1,0) -> -0.67230198 | E44: =IFERROR(E43/D43-1,0) -> 0.2497644 | F44: =IFERROR(F43/E43-1,0) -> 0.30457231 | G44: =IFERROR(G43/F43-1,0) -> -0.45431225 | H44: =IFERROR(H43/G43-1,0) -> 0.4907208 | I44: =IFERROR(I43/H43-1,0) -> 1.5135914 | J44: =IFERROR(J43/I43-1,0) -> 0.12704361 | K44: =IFERROR(K43/J43-1,0) -> 0.13801817 | ... M44: =IFERROR(M43/L43-1,0) -> 0.19660219
B46: Divident per share | C46: =-IFERROR('Data Sheet'!B31/C41,0) -> -3.5000208 | D46: =-IFERROR('Data Sheet'!C31/D41,0) -> -2 | E46: =-IFERROR('Data Sheet'!D31/E41,0) -> -2.7500104 | F46: =-IFERROR('Data Sheet'!E31/F41,0) -> -4 | G46: =-IFERROR('Data Sheet'!F31/G41,0) -> -7.5000208 | H46: =-IFERROR('Data Sheet'!G31/H41,0) -> -10 | I46: =-IFERROR('Data Sheet'!H31/I41,0) -> -11.500021 | J46: =-IFERROR('Data Sheet'!I31/J41,0) -> -13.500021 | ... M46: =-IFERROR('Data Sheet'!L31/M41,0) -> 0
B47: Dividend Payout ratio | C47: =IFERROR(C46/C43,0) -> -0.10716282 | D47: =IFERROR(D46/D43,0) -> -0.18686574 | E47: =IFERROR(E46/E43,0) -> -0.20559184 | F47: =IFERROR(F46/F43,0) -> -0.22922573 | G47: =IFERROR(G46/G43,0) -> -0.7876289 | H47: =IFERROR(H46/H43,0) -> -0.70447058 | I47: =IFERROR(I46/I43,0) -> -0.32230482 | J47: =IFERROR(J46/J43,0) -> -0.33570816 | ... M47: =IFERROR(M46/M43,0) -> 0
B49: Retained Earnings | C49: =IFERROR(IF(C43>C46,1-C47,0),0) -> 1.1071628 | D49: =IFERROR(IF(D43>D46,1-D47,0),0) -> 1.1868657 | E49: =IFERROR(IF(E43>E46,1-E47,0),0) -> 1.2055918 | F49: =IFERROR(IF(F43>F46,1-F47,0),0) -> 1.2292257 | G49: =IFERROR(IF(G43>G46,1-G47,0),0) -> 1.7876289 | H49: =IFERROR(IF(H43>H46,1-H47,0),0) -> 1.7044706 | I49: =IFERROR(IF(I43>I46,1-I47,0),0) -> 1.3223048 | J49: =IFERROR(IF(J43>J46,1-J47,0),0) -> 1.3357082 | ... M49: =IFERROR(IF(M43>M46,1-M47,0),0) -> 1
A51: # | B51: Balance sheet
B53: Equity Share Capital | C53: =IFERROR('Data Sheet'!B57,0) -> 239.93 | D53: =IFERROR('Data Sheet'!C57,0) -> 239.93 | E53: =IFERROR('Data Sheet'!D57,0) -> 239.93 | F53: =IFERROR('Data Sheet'!E57,0) -> 239.93 | G53: =IFERROR('Data Sheet'!F57,0) -> 239.93 | H53: =IFERROR('Data Sheet'!G57,0) -> 239.93 | I53: =IFERROR('Data Sheet'!H57,0) -> 239.93 | J53: =IFERROR('Data Sheet'!I57,0) -> 239.93 | ... L53: =IFERROR('Data Sheet'!K57,0) -> 239.93
B54: Reserves | C54: =IFERROR('Data Sheet'!B58,0) -> 36399.74 | D54: =IFERROR('Data Sheet'!C58,0) -> 38074.18 | E54: =IFERROR('Data Sheet'!D58,0) -> 41169.13 | F54: =IFERROR('Data Sheet'!E58,0) -> 45024.52 | G54: =IFERROR('Data Sheet'!F58,0) -> 46222.85 | H54: =IFERROR('Data Sheet'!G58,0) -> 47771.29 | I54: =IFERROR('Data Sheet'!H58,0) -> 55755.45 | J54: =IFERROR('Data Sheet'!I58,0) -> 63426.82 | ... L54: =IFERROR('Data Sheet'!K58,0) -> 83330.16
B55: Borrowings | C55: =IFERROR('Data Sheet'!B59,0) -> 9831.77 | D55: =IFERROR('Data Sheet'!C59,0) -> 10385.27 | E55: =IFERROR('Data Sheet'!D59,0) -> 10514.36 | F55: =IFERROR('Data Sheet'!E59,0) -> 8314.88 | G55: =IFERROR('Data Sheet'!F59,0) -> 3868.58 | H55: =IFERROR('Data Sheet'!G59,0) -> 1290.3 | I55: =IFERROR('Data Sheet'!H59,0) -> 6885.87 | J55: =IFERROR('Data Sheet'!I59,0) -> 3273.67 | ... L55: =IFERROR('Data Sheet'!K59,0) -> 4627.32
B56: Other Liabilities | C56: =IFERROR('Data Sheet'!B60,0) -> 14624.01 | D56: =IFERROR('Data Sheet'!C60,0) -> 15598.01 | E56: =IFERROR('Data Sheet'!D60,0) -> 12666.11 | F56: =IFERROR('Data Sheet'!E60,0) -> 14614.99 | G56: =IFERROR('Data Sheet'!F60,0) -> 17290.86 | H56: =IFERROR('Data Sheet'!G60,0) -> 20474.39 | I56: =IFERROR('Data Sheet'!H60,0) -> 17830.65 | J56: =IFERROR('Data Sheet'!I60,0) -> 18387.37 | ... L56: =IFERROR('Data Sheet'!K60,0) -> 20587.81
B57: Total Liabilities | C57: =IFERROR('Data Sheet'!B61,0) -> 61095.45 | D57: =IFERROR('Data Sheet'!C61,0) -> 64297.39 | E57: =IFERROR('Data Sheet'!D61,0) -> 64589.53 | F57: =IFERROR('Data Sheet'!E61,0) -> 68194.32 | G57: =IFERROR('Data Sheet'!F61,0) -> 67622.22 | H57: =IFERROR('Data Sheet'!G61,0) -> 69775.91 | I57: =IFERROR('Data Sheet'!H61,0) -> 80711.9 | J57: =IFERROR('Data Sheet'!I61,0) -> 85327.79 | ... L57: =IFERROR('Data Sheet'!K61,0) -> 108785.22
B59: Fixed Assets Net Block | C59: =IFERROR('Data Sheet'!B62,0) -> 17675.17 | D59: =IFERROR('Data Sheet'!C62,0) -> 18852.65 | E59: =IFERROR('Data Sheet'!D62,0) -> 21836.54 | F59: =IFERROR('Data Sheet'!E62,0) -> 22846.91 | G59: =IFERROR('Data Sheet'!F62,0) -> 21552.98 | H59: =IFERROR('Data Sheet'!G62,0) -> 22665.16 | I59: =IFERROR('Data Sheet'!H62,0) -> 24065.44 | J59: =IFERROR('Data Sheet'!I62,0) -> 23248.15 | ... L59: =IFERROR('Data Sheet'!K62,0) -> 34493.35
B60: Capital Work in Progress | C60: =IFERROR('Data Sheet'!B63,0) -> 2801.38 | D60: =IFERROR('Data Sheet'!C63,0) -> 2465.16 | E60: =IFERROR('Data Sheet'!D63,0) -> 1411.15 | F60: =IFERROR('Data Sheet'!E63,0) -> 1220.34 | G60: =IFERROR('Data Sheet'!F63,0) -> 1566.83 | H60: =IFERROR('Data Sheet'!G63,0) -> 1286.8 | I60: =IFERROR('Data Sheet'!H63,0) -> 4973.16 | J60: =IFERROR('Data Sheet'!I63,0) -> 5353.88 | ... L60: =IFERROR('Data Sheet'!K63,0) -> 1380.65
B61: Investments | C61: =IFERROR('Data Sheet'!B64,0) -> 1191.88 | D61: =IFERROR('Data Sheet'!C64,0) -> 7142.87 | E61: =IFERROR('Data Sheet'!D64,0) -> 7902.53 | F61: =IFERROR('Data Sheet'!E64,0) -> 10143.11 | G61: =IFERROR('Data Sheet'!F64,0) -> 9612.45 | H61: =IFERROR('Data Sheet'!G64,0) -> 12848.59 | I61: =IFERROR('Data Sheet'!H64,0) -> 14824.34 | J61: =IFERROR('Data Sheet'!I64,0) -> 15025.77 | ... L61: =IFERROR('Data Sheet'!K64,0) -> 24722.52
B62: Other Assets | C62: =IFERROR('Data Sheet'!B65-SUM('Data Sheet'!B67:B69),0) -> 10250.76 | D62: =IFERROR('Data Sheet'!C65-SUM('Data Sheet'!C67:C69),0) -> 11211.36 | E62: =IFERROR('Data Sheet'!D65-SUM('Data Sheet'!D67:D69),0) -> 9393.53 | F62: =IFERROR('Data Sheet'!E65-SUM('Data Sheet'!E67:E69),0) -> 10200.18 | G62: =IFERROR('Data Sheet'!F65-SUM('Data Sheet'!F67:F69),0) -> 10386.03 | H62: =IFERROR('Data Sheet'!G65-SUM('Data Sheet'!G67:G69),0) -> 8532.29 | I62: =IFERROR('Data Sheet'!H65-SUM('Data Sheet'!H67:H69),0) -> 9127.11 | J62: =IFERROR('Data Sheet'!I65-SUM('Data Sheet'!I67:I69),0) -> 10061.65 | ... L62: =IFERROR('Data Sheet'!K65-SUM('Data Sheet'!K67:K69),0) -> 9583.02
B63: Total Non Current Assets | C63: =SUM(C59:C62) -> 31919.19 | D63: =SUM(D59:D62) -> 39672.04 | E63: =SUM(E59:E62) -> 40543.75 | F63: =SUM(F59:F62) -> 44410.54 | G63: =SUM(G59:G62) -> 43118.29 | H63: =SUM(H59:H62) -> 45332.84 | I63: =SUM(I59:I62) -> 52990.05 | J63: =SUM(J59:J62) -> 53689.45 | ... L63: =SUM(L59:L62) -> 70179.54
C65: =IFERROR('Data Sheet'!B67,0) -> 7202.61 | D65: =IFERROR('Data Sheet'!C67,0) -> 7815.28 | E65: =IFERROR('Data Sheet'!D67,0) -> 8884.2 | F65: =IFERROR('Data Sheet'!E67,0) -> 9421.24 | G65: =IFERROR('Data Sheet'!F67,0) -> 9061.4 | H65: =IFERROR('Data Sheet'!G67,0) -> 10484.59 | I65: =IFERROR('Data Sheet'!H67,0) -> 11438.51 | J65: =IFERROR('Data Sheet'!I67,0) -> 11249.37 | ... L65: =IFERROR('Data Sheet'!K67,0) -> 15509.67
B66: Inventory | C66: =IFERROR('Data Sheet'!B68,0) -> 6832.81 | D66: =IFERROR('Data Sheet'!C68,0) -> 6880.69 | E66: =IFERROR('Data Sheet'!D68,0) -> 7885.98 | F66: =IFERROR('Data Sheet'!E68,0) -> 7874.99 | G66: =IFERROR('Data Sheet'!F68,0) -> 8997.02 | H66: =IFERROR('Data Sheet'!G68,0) -> 8925.13 | I66: =IFERROR('Data Sheet'!H68,0) -> 10513.05 | J66: =IFERROR('Data Sheet'!I68,0) -> 9868.29 | ... L66: =IFERROR('Data Sheet'!K68,0) -> 11492.93
B67: Cash & Bank | C67: =IFERROR('Data Sheet'!B69,0) -> 15140.84 | D67: =IFERROR('Data Sheet'!C69,0) -> 9929.38 | E67: =IFERROR('Data Sheet'!D69,0) -> 7275.6 | F67: =IFERROR('Data Sheet'!E69,0) -> 6487.55 | G67: =IFERROR('Data Sheet'!F69,0) -> 6445.51 | H67: =IFERROR('Data Sheet'!G69,0) -> 5033.35 | I67: =IFERROR('Data Sheet'!H69,0) -> 5770.29 | J67: =IFERROR('Data Sheet'!I69,0) -> 10520.68 | ... L67: =IFERROR('Data Sheet'!K69,0) -> 11603.08
B68: Total Current Assets | C68: =IFERROR(SUM(C65:C67),0) -> 29176.26 | D68: =IFERROR(SUM(D65:D67),0) -> 24625.35 | E68: =IFERROR(SUM(E65:E67),0) -> 24045.78 | F68: =IFERROR(SUM(F65:F67),0) -> 23783.78 | G68: =IFERROR(SUM(G65:G67),0) -> 24503.93 | H68: =IFERROR(SUM(H65:H67),0) -> 24443.07 | I68: =IFERROR(SUM(I65:I67),0) -> 27721.85 | J68: =IFERROR(SUM(J65:J67),0) -> 31638.34 | ... L68: =IFERROR(SUM(L65:L67),0) -> 38605.68
B70: Total Assets | C70: =IFERROR(C68+C63,0) -> 61095.45 | D70: =IFERROR(D68+D63,0) -> 64297.39 | E70: =IFERROR(E68+E63,0) -> 64589.53 | F70: =IFERROR(F68+F63,0) -> 68194.32 | G70: =IFERROR(G68+G63,0) -> 67622.22 | H70: =IFERROR(H68+H63,0) -> 69775.91 | I70: =IFERROR(I68+I63,0) -> 80711.9 | J70: =IFERROR(J68+J63,0) -> 85327.79 | ... L70: =IFERROR(L68+L63,0) -> 108785.22
B72: Check | C72: =C70=C57 -> TRUE | D72: =D70=D57 -> TRUE | E72: =E70=E57 -> TRUE | F72: =F70=F57 -> TRUE | G72: =G70=G57 -> TRUE | H72: =H70=H57 -> TRUE | I72: =I70=I57 -> TRUE | J72: =J70=J57 -> TRUE | ... L72: =L70=L57 -> TRUE
A74: # | B74: Cash Flow Statements
B75: Opreating Activities
B76: Profit from operations | C76: =IFERROR('CashFlow Data'!C4,0) -> 9549 | D76: =IFERROR('CashFlow Data'!D4,0) -> 4861 | E76: =IFERROR('CashFlow Data'!E4,0) -> 5779 | F76: =IFERROR('CashFlow Data'!F4,0) -> 7002 | G76: =IFERROR('CashFlow Data'!G4,0) -> 4609 | H76: =IFERROR('CashFlow Data'!H4,0) -> 6456 | I76: =IFERROR('CashFlow Data'!I4,0) -> 12131 | J76: =IFERROR('CashFlow Data'!J4,0) -> 12642 | ... L76: =IFERROR('CashFlow Data'!L4,0) -> 16001
B77: Receivables | C77: =IFERROR('CashFlow Data'!C5,0) -> -293 | D77: =IFERROR('CashFlow Data'!D5,0) -> -773 | E77: =IFERROR('CashFlow Data'!E5,0) -> -858 | F77: =IFERROR('CashFlow Data'!F5,0) -> -374 | G77: =IFERROR('CashFlow Data'!G5,0) -> 94 | H77: =IFERROR('CashFlow Data'!H5,0) -> -1342 | I77: =IFERROR('CashFlow Data'!I5,0) -> -953 | J77: =IFERROR('CashFlow Data'!J5,0) -> 353 | ... L77: =IFERROR('CashFlow Data'!L5,0) -> -2009
B78: Inventory | C78: =IFERROR('CashFlow Data'!C6,0) -> -345 | D78: =IFERROR('CashFlow Data'!D6,0) -> -4 | E78: =IFERROR('CashFlow Data'!E6,0) -> -709 | F78: =IFERROR('CashFlow Data'!F6,0) -> 257 | G78: =IFERROR('CashFlow Data'!G6,0) -> -1080 | H78: =IFERROR('CashFlow Data'!H6,0) -> 307 | I78: =IFERROR('CashFlow Data'!I6,0) -> -1202 | J78: =IFERROR('CashFlow Data'!J6,0) -> 599 | ... L78: =IFERROR('CashFlow Data'!L6,0) -> -52
B79: Payables | C79: =IFERROR('CashFlow Data'!C7,0) -> 735 | D79: =IFERROR('CashFlow Data'!D7,0) -> 383 | E79: =IFERROR('CashFlow Data'!E7,0) -> -854 | F79: =IFERROR('CashFlow Data'!F7,0) -> -210 | G79: =IFERROR('CashFlow Data'!G7,0) -> 381 | H79: =IFERROR('CashFlow Data'!H7,0) -> 370 | I79: =IFERROR('CashFlow Data'!I7,0) -> 1182 | J79: =IFERROR('CashFlow Data'!J7,0) -> 250 | ... L79: =IFERROR('CashFlow Data'!L7,0) -> 1057
B80: Loans Advances | C80: =IFERROR('CashFlow Data'!C8,0) -> 0 | D80: =IFERROR('CashFlow Data'!D8,0) -> 0 | E80: =IFERROR('CashFlow Data'!E8,0) -> 0 | F80: =IFERROR('CashFlow Data'!F8,0) -> 0 | G80: =IFERROR('CashFlow Data'!G8,0) -> 0 | H80: =IFERROR('CashFlow Data'!H8,0) -> 0 | I80: =IFERROR('CashFlow Data'!I8,0) -> 0 | J80: =IFERROR('CashFlow Data'!J8,0) -> 0 | ... L80: =IFERROR('CashFlow Data'!L8,0) -> 0
B81: Other WC items | C81: =IFERROR('CashFlow Data'!C9,0) -> -506 | D81: =IFERROR('CashFlow Data'!D9,0) -> 182 | E81: =IFERROR('CashFlow Data'!E9,0) -> -275 | F81: =IFERROR('CashFlow Data'!F9,0) -> 1226 | G81: =IFERROR('CashFlow Data'!G9,0) -> 3169 | H81: =IFERROR('CashFlow Data'!H9,0) -> 2224 | I81: =IFERROR('CashFlow Data'!I9,0) -> -4689 | J81: =IFERROR('CashFlow Data'!J9,0) -> -139 | ... L81: =IFERROR('CashFlow Data'!L9,0) -> -264
B82: Working capital changes | C82: =IFERROR('CashFlow Data'!C10,0) -> -409 | D82: =IFERROR('CashFlow Data'!D10,0) -> -212 | E82: =IFERROR('CashFlow Data'!E10,0) -> -2696 | F82: =IFERROR('CashFlow Data'!F10,0) -> 899 | G82: =IFERROR('CashFlow Data'!G10,0) -> 2564 | H82: =IFERROR('CashFlow Data'!H10,0) -> 1559 | I82: =IFERROR('CashFlow Data'!I10,0) -> -5662 | J82: =IFERROR('CashFlow Data'!J10,0) -> 1062 | ... L82: =IFERROR('CashFlow Data'!L10,0) -> -1268
B83: Direct taxes | C83: =IFERROR('CashFlow Data'!C11,0) -> -2057 | D83: =IFERROR('CashFlow Data'!D11,0) -> -742 | E83: =IFERROR('CashFlow Data'!E11,0) -> -886 | F83: =IFERROR('CashFlow Data'!F11,0) -> -1346 | G83: =IFERROR('CashFlow Data'!G11,0) -> -1003 | H83: =IFERROR('CashFlow Data'!H11,0) -> 969 | I83: =IFERROR('CashFlow Data'!I11,0) -> -1510 | J83: =IFERROR('CashFlow Data'!J11,0) -> -1569 | ... L83: =IFERROR('CashFlow Data'!L11,0) -> -2314
B84: Cash from Opr Activities | C84: =SUM(C76:C83) -> 6674 | D84: =SUM(D76:D83) -> 3695 | E84: =SUM(E76:E83) -> -499 | F84: =SUM(F76:F83) -> 7454 | G84: =SUM(G76:G83) -> 8734 | H84: =SUM(H76:H83) -> 10543 | I84: =SUM(I76:I83) -> -703 | J84: =SUM(J76:J83) -> 13198 | ... L84: =SUM(L76:L83) -> 11151
B86: Investing Activities
B87: Fixed assets purchased | C87: =IFERROR('CashFlow Data'!C13,0) -> -3693 | D87: =IFERROR('CashFlow Data'!D13,0) -> -1961 | E87: =IFERROR('CashFlow Data'!E13,0) -> -3213 | F87: =IFERROR('CashFlow Data'!F13,0) -> -1542 | G87: =IFERROR('CashFlow Data'!G13,0) -> -1170 | H87: =IFERROR('CashFlow Data'!H13,0) -> -1495 | I87: =IFERROR('CashFlow Data'!I13,0) -> -2086 | J87: =IFERROR('CashFlow Data'!J13,0) -> -2202 | ... L87: =IFERROR('CashFlow Data'!L13,0) -> -3609
B88: Fixed assets sold | C88: =IFERROR('CashFlow Data'!C14,0) -> 102 | D88: =IFERROR('CashFlow Data'!D14,0) -> 66 | E88: =IFERROR('CashFlow Data'!E14,0) -> 50 | F88: =IFERROR('CashFlow Data'!F14,0) -> 92 | G88: =IFERROR('CashFlow Data'!G14,0) -> 97 | H88: =IFERROR('CashFlow Data'!H14,0) -> 61 | I88: =IFERROR('CashFlow Data'!I14,0) -> 21 | J88: =IFERROR('CashFlow Data'!J14,0) -> 31 | ... L88: =IFERROR('CashFlow Data'!L14,0) -> 96
B89: Investments purchased | C89: =IFERROR('CashFlow Data'!C15,0) -> -38831 | D89: =IFERROR('CashFlow Data'!D15,0) -> -40587 | E89: =IFERROR('CashFlow Data'!E15,0) -> -35396 | F89: =IFERROR('CashFlow Data'!F15,0) -> -33445 | G89: =IFERROR('CashFlow Data'!G15,0) -> -18542 | H89: =IFERROR('CashFlow Data'!H15,0) -> -24135 | I89: =IFERROR('CashFlow Data'!I15,0) -> -21809 | J89: =IFERROR('CashFlow Data'!J15,0) -> -29004 | ... L89: =IFERROR('CashFlow Data'!L15,0) -> -30804
B90: Investments sold | C90: =IFERROR('CashFlow Data'!C16,0) -> 39194 | D90: =IFERROR('CashFlow Data'!D16,0) -> 34992 | E90: =IFERROR('CashFlow Data'!E16,0) -> 35207 | F90: =IFERROR('CashFlow Data'!F16,0) -> 31894 | G90: =IFERROR('CashFlow Data'!G16,0) -> 19709 | H90: =IFERROR('CashFlow Data'!H16,0) -> 20702 | I90: =IFERROR('CashFlow Data'!I16,0) -> 20897 | J90: =IFERROR('CashFlow Data'!J16,0) -> 30094 | ... L90: =IFERROR('CashFlow Data'!L16,0) -> 26167
B91: Interest received | C91: =IFERROR('CashFlow Data'!C17,0) -> 337 | D91: =IFERROR('CashFlow Data'!D17,0) -> 510 | E91: =IFERROR('CashFlow Data'!E17,0) -> 684 | F91: =IFERROR('CashFlow Data'!F17,0) -> 338 | G91: =IFERROR('CashFlow Data'!G17,0) -> 72 | H91: =IFERROR('CashFlow Data'!H17,0) -> 76 | I91: =IFERROR('CashFlow Data'!I17,0) -> 318 | J91: =IFERROR('CashFlow Data'!J17,0) -> 613 | ... L91: =IFERROR('CashFlow Data'!L17,0) -> 705
B92: Dividends received | C92: =IFERROR('CashFlow Data'!C18,0) -> 42 | D92: =IFERROR('CashFlow Data'!D18,0) -> 37 | E92: =IFERROR('CashFlow Data'!E18,0) -> 22 | F92: =IFERROR('CashFlow Data'!F18,0) -> 56 | G92: =IFERROR('CashFlow Data'!G18,0) -> 138 | H92: =IFERROR('CashFlow Data'!H18,0) -> 134 | I92: =IFERROR('CashFlow Data'!I18,0) -> 132 | J92: =IFERROR('CashFlow Data'!J18,0) -> 99 | ... L92: =IFERROR('CashFlow Data'!L18,0) -> 59
B93: Investment in group cos | C93: =IFERROR('CashFlow Data'!C19,0) -> 0 | D93: =IFERROR('CashFlow Data'!D19,0) -> 0 | E93: =IFERROR('CashFlow Data'!E19,0) -> 0 | F93: =IFERROR('CashFlow Data'!F19,0) -> 0 | G93: =IFERROR('CashFlow Data'!G19,0) -> 0 | H93: =IFERROR('CashFlow Data'!H19,0) -> -15 | I93: =IFERROR('CashFlow Data'!I19,0) -> -155 | J93: =IFERROR('CashFlow Data'!J19,0) -> -87 | ... L93: =IFERROR('CashFlow Data'!L19,0) -> 0
B94: Redemp n Canc of Shares | C94: =IFERROR('CashFlow Data'!C20,0) -> 0 | D94: =IFERROR('CashFlow Data'!D20,0) -> 0 | E94: =IFERROR('CashFlow Data'!E20,0) -> 0 | F94: =IFERROR('CashFlow Data'!F20,0) -> 0 | G94: =IFERROR('CashFlow Data'!G20,0) -> 0 | H94: =IFERROR('CashFlow Data'!H20,0) -> 24 | I94: =IFERROR('CashFlow Data'!I20,0) -> 0 | J94: =IFERROR('CashFlow Data'!J20,0) -> 0 | ... L94: =IFERROR('CashFlow Data'!L20,0) -> 0
B95: Acquisition of companies | C95: =IFERROR('CashFlow Data'!C21,0) -> -167 | D95: =IFERROR('CashFlow Data'!D21,0) -> -86 | E95: =IFERROR('CashFlow Data'!E21,0) -> -23 | F95: =IFERROR('CashFlow Data'!F21,0) -> 0 | G95: =IFERROR('CashFlow Data'!G21,0) -> -62 | H95: =IFERROR('CashFlow Data'!H21,0) -> -740 | I95: =IFERROR('CashFlow Data'!I21,0) -> -4686 | J95: =IFERROR('CashFlow Data'!J21,0) -> -143 | ... L95: =IFERROR('CashFlow Data'!L21,0) -> -3405
B96: Inter corporate deposits | C96: 0 | D96: 0 | E96: 0 | F96: 0 | G96: 0 | H96: 0 | I96: 0 | J96: 0 | K96: 0 | L96: 0
B97: Other investing items | C97: =IFERROR('CashFlow Data'!C22,0) -> -1170 | D97: =IFERROR('CashFlow Data'!D22,0) -> 3923 | E97: =IFERROR('CashFlow Data'!E22,0) -> 2357 | F97: =IFERROR('CashFlow Data'!F22,0) -> 382 | G97: =IFERROR('CashFlow Data'!G22,0) -> 165 | H97: =IFERROR('CashFlow Data'!H22,0) -> -167 | I97: =IFERROR('CashFlow Data'!I22,0) -> 148 | J97: =IFERROR('CashFlow Data'!J22,0) -> -164 | ... L97: =IFERROR('CashFlow Data'!L22,0) -> -553
B98: Cash from Invest Activities | C98: =SUM(C87:C97) -> -4186 | D98: =SUM(D87:D97) -> -3106 | E98: =SUM(E87:E97) -> -312 | F98: =SUM(F87:F97) -> -2225 | G98: =SUM(G87:G97) -> 407 | H98: =SUM(H87:H97) -> -5555 | I98: =SUM(I87:I97) -> -7220 | J98: =SUM(J87:J97) -> -763 | ... L98: =SUM(L87:L97) -> -11344
B100: Financing Activities
B101: Proceeds from shares | C101: =IFERROR('CashFlow Data'!C24,0) -> 2 | D101: =IFERROR('CashFlow Data'!D24,0) -> 1 | E101: =IFERROR('CashFlow Data'!E24,0) -> 0 | F101: =IFERROR('CashFlow Data'!F24,0) -> 0 | G101: =IFERROR('CashFlow Data'!G24,0) -> 425 | H101: =IFERROR('CashFlow Data'!H24,0) -> 0 | I101: =IFERROR('CashFlow Data'!I24,0) -> 0 | J101: =IFERROR('CashFlow Data'!J24,0) -> 0 | ... L101: =IFERROR('CashFlow Data'!L24,0) -> 0
B102: Redemption of debentures | C102: 0 | D102: 0 | E102: 0 | F102: 0 | G102: 0 | H102: 0 | I102: 0 | J102: 0 | K102: 0 | L102: 0
B103: Proceeds from borrowings | C103: =IFERROR('CashFlow Data'!C25,0) -> 0 | D103: =IFERROR('CashFlow Data'!D25,0) -> 0 | E103: =IFERROR('CashFlow Data'!E25,0) -> 17698 | F103: =IFERROR('CashFlow Data'!F25,0) -> 10552 | G103: =IFERROR('CashFlow Data'!G25,0) -> 6603 | H103: =IFERROR('CashFlow Data'!H25,0) -> 1763 | I103: =IFERROR('CashFlow Data'!I25,0) -> 8160 | J103: =IFERROR('CashFlow Data'!J25,0) -> 4573 | ... L103: =IFERROR('CashFlow Data'!L25,0) -> 5322
B104: Repayment of borrowings | C104: =IFERROR('CashFlow Data'!C26,0) -> 0 | D104: =IFERROR('CashFlow Data'!D26,0) -> 0 | E104: =IFERROR('CashFlow Data'!E26,0) -> -16807 | F104: =IFERROR('CashFlow Data'!F26,0) -> -13893 | G104: =IFERROR('CashFlow Data'!G26,0) -> -10802 | H104: =IFERROR('CashFlow Data'!H26,0) -> -4400 | I104: =IFERROR('CashFlow Data'!I26,0) -> -3030 | J104: =IFERROR('CashFlow Data'!J26,0) -> -7963 | ... L104: =IFERROR('CashFlow Data'!L26,0) -> -3410
B105: Interest paid fin | C105: =IFERROR('CashFlow Data'!C27,0) -> -334 | D105: =IFERROR('CashFlow Data'!D27,0) -> -477 | E105: =IFERROR('CashFlow Data'!E27,0) -> -461 | F105: =IFERROR('CashFlow Data'!F27,0) -> -272 | G105: =IFERROR('CashFlow Data'!G27,0) -> -144 | H105: =IFERROR('CashFlow Data'!H27,0) -> -73 | I105: =IFERROR('CashFlow Data'!I27,0) -> -132 | J105: =IFERROR('CashFlow Data'!J27,0) -> -219 | ... L105: =IFERROR('CashFlow Data'!L27,0) -> 0
B106: Dividends paid | C106: =IFERROR('CashFlow Data'!C28,0) -> -243 | D106: =IFERROR('CashFlow Data'!D28,0) -> -813 | E106: =IFERROR('CashFlow Data'!E28,0) -> -1326 | F106: =IFERROR('CashFlow Data'!F28,0) -> -1399 | G106: =IFERROR('CashFlow Data'!G28,0) -> -1586 | H106: =IFERROR('CashFlow Data'!H28,0) -> -2169 | I106: =IFERROR('CashFlow Data'!I28,0) -> -2520 | J106: =IFERROR('CashFlow Data'!J28,0) -> -2901 | ... L106: =IFERROR('CashFlow Data'!L28,0) -> -3938
B107: Financial liabilities | C107: =IFERROR('CashFlow Data'!C29,0) -> 0 | D107: =IFERROR('CashFlow Data'!D29,0) -> 0 | E107: =IFERROR('CashFlow Data'!E29,0) -> 0 | F107: =IFERROR('CashFlow Data'!F29,0) -> 0 | G107: =IFERROR('CashFlow Data'!G29,0) -> -118 | H107: =IFERROR('CashFlow Data'!H29,0) -> -129 | I107: =IFERROR('CashFlow Data'!I29,0) -> -101 | J107: =IFERROR('CashFlow Data'!J29,0) -> -123 | ... L107: =IFERROR('CashFlow Data'!L29,0) -> -483
B108: Other financing items | C108: =IFERROR('CashFlow Data'!C30,0) -> -1711 | D108: =IFERROR('CashFlow Data'!D30,0) -> -250 | E108: =IFERROR('CashFlow Data'!E30,0) -> -1835 | F108: =IFERROR('CashFlow Data'!F30,0) -> -702 | G108: =IFERROR('CashFlow Data'!G30,0) -> -358 | H108: =IFERROR('CashFlow Data'!H30,0) -> -186 | I108: =IFERROR('CashFlow Data'!I30,0) -> 0 | J108: =IFERROR('CashFlow Data'!J30,0) -> -77 | ... L108: =IFERROR('CashFlow Data'!L30,0) -> -4
B109: Cash from Fin Activities | C109: =SUM(C101:C108) -> -2286 | D109: =SUM(D101:D108) -> -1539 | E109: =SUM(E101:E108) -> -2731 | F109: =SUM(F101:F108) -> -5714 | G109: =SUM(G101:G108) -> -5980 | H109: =SUM(H101:H108) -> -5194 | I109: =SUM(I101:I108) -> 2377 | J109: =SUM(J101:J108) -> -6710 | ... L109: =SUM(L101:L108) -> -2513
B111: Net Cash Flow | C111: =IFERROR(C84+C98+C109,0) -> 202 | D111: =IFERROR(D84+D98+D109,0) -> -950 | E111: =IFERROR(E84+E98+E109,0) -> -3542 | F111: =IFERROR(F84+F98+F109,0) -> -485 | G111: =IFERROR(G84+G98+G109,0) -> 3161 | H111: =IFERROR(H84+H98+H109,0) -> -206 | I111: =IFERROR(I84+I98+I109,0) -> -5546 | J111: =IFERROR(J84+J98+J109,0) -> 5725 | ... L111: =IFERROR(L84+L98+L109,0) -> -2706
A113: # | B113: Cash Flow Statements
B115: Cash From Opr Activities | C115: =IFERROR('Data Sheet'!B82,0) -> 7082.21 | D115: =IFERROR('Data Sheet'!C82,0) -> 3907.15 | E115: =IFERROR('Data Sheet'!D82,0) -> 2196.45 | F115: =IFERROR('Data Sheet'!E82,0) -> 6554.77 | G115: =IFERROR('Data Sheet'!F82,0) -> 6170.37 | H115: =IFERROR('Data Sheet'!G82,0) -> 8984.54 | I115: =IFERROR('Data Sheet'!H82,0) -> 4959.33 | J115: =IFERROR('Data Sheet'!I82,0) -> 12134.98 | ... L115: =IFERROR('Data Sheet'!K82,0) -> 12419.18
B117: Cash from Investing Activity | C117: =IFERROR('Data Sheet'!B83,0) -> -4186.15 | D117: =IFERROR('Data Sheet'!C83,0) -> -3103.8 | E117: =IFERROR('Data Sheet'!D83,0) -> -310.08 | F117: =IFERROR('Data Sheet'!E83,0) -> -2225.32 | G117: =IFERROR('Data Sheet'!F83,0) -> 406.53 | H117: =IFERROR('Data Sheet'!G83,0) -> -5555.86 | I117: =IFERROR('Data Sheet'!H83,0) -> -7219.92 | J117: =IFERROR('Data Sheet'!I83,0) -> -762.9 | ... L117: =IFERROR('Data Sheet'!K83,0) -> -11344.05
B119: Cash from Financing Activity | C119: =IFERROR('Data Sheet'!B84,0) -> -2285.39 | D119: =IFERROR('Data Sheet'!C84,0) -> -1539.26 | E119: =IFERROR('Data Sheet'!D84,0) -> -2730.52 | F119: =IFERROR('Data Sheet'!E84,0) -> -5715.14 | G119: =IFERROR('Data Sheet'!F84,0) -> -5980.48 | H119: =IFERROR('Data Sheet'!G84,0) -> -5193.46 | I119: =IFERROR('Data Sheet'!H84,0) -> 2376.07 | J119: =IFERROR('Data Sheet'!I84,0) -> -6710.16 | ... L119: =IFERROR('Data Sheet'!K84,0) -> -2512.55
B121: Net Cash Flow | C121: =SUM(C119,C117,C115) -> 610.67 | D121: =SUM(D119,D117,D115) -> -735.91 | E121: =SUM(E119,E117,E115) -> -844.15 | F121: =SUM(F119,F117,F115) -> -1385.69 | G121: =SUM(G119,G117,G115) -> 596.42 | H121: =SUM(H119,H117,H115) -> -1764.78 | I121: =SUM(I119,I117,I115) -> 115.48 | J121: =SUM(J119,J117,J115) -> 4661.92 | ... L121: =SUM(L119,L117,L115) -> -1437.42

Sheet Data Sheet
A1: COMPANY NAME | B1: SUN PHARMACEUTICAL INDUSTRIES LTD | E1: SUN PHARMACEUTICAL INDUSTRIES LTD
A2: LATEST VERSION | B2: 2.1 | E2: PLEASE DO NOT MAKE ANY CHANGES TO THIS SHEET
A3: CURRENT VERSION | B3: 2.1
A5: META
A6: Number of shares | B6: =IF(B9>0, B9/B8, 0) -> 239.96033
A7: Face Value | B7: 1
A8: Current Price | B8: 1789.65
A9: Market Capitalization | B9: 429445.01
A15: PROFIT & LOSS
A16: Report Date | B16: 42825 | C16: 43190 | D16: 43555 | E16: 43921 | F16: 44286 | G16: 44651 | H16: 45016 | I16: 45382 | J16: 45747 | K16: 46112
A17: Sales | B17: 31578.44 | C17: 26489.46 | D17: 29065.91 | E17: 32837.5 | F17: 33498.14 | G17: 38654.49 | H17: 43885.68 | I17: 48496.85 | J17: 52578.44 | K17: 58462.04
A18: Raw Material Cost | B18: 8402.37 | C18: 7193.98 | D18: 8302.08 | E18: 8929.6 | F18: 9328.3 | G18: 10459.15 | H18: 11349.07 | I18: 10370.48 | J18: 10597.05 | K18: 11200.55
A19: Change in Inventory | B19: 271.63 | C19: -230.7 | D19: 433.11 | E19: -300.85 | F19: 638.22 | G19: 107.61 | H19: 686.91 | I19: -292.13 | J19: -150.31 | K19: -343.13
A20: Power and Fuel | B20: 525.09 | C20: 559.97 | D20: 613.6 | E20: 621.89 | F20: 627.09 | G20: 702.78 | H20: 830.05 | I20: 760.78 | J20: 750.4
A21: Other Mfr. Exp | B21: 1973.46 | C21: 1828.35 | D21: 1884.71 | E21: 1690 | F21: 1723.78 | G21: 1880.71 | H21: 1936.77 | I21: 2186.62 | J21: 2261.24
A22: Employee Cost | B22: 4902.3 | C22: 5367.05 | D22: 5967.09 | E22: 6362.35 | F22: 6862.23 | G22: 7300.83 | H22: 8296.03 | I22: 9429.06 | J22: 9973.12 | K22: 11418.86
A23: Selling and admin | B23: 5224.61 | C23: 4727 | D23: 5350.33 | E23: 6995.37 | F23: 6283.41 | G23: 7366.88 | H23: 9482.36 | I23: 11033.19 | J23: 12222.92
A24: Other Expenses | B24: 720.22 | C24: 950.99 | D24: 1004.23 | E24: 954.6 | F24: 841.59 | G24: 794.18 | H24: 1027.87 | I24: 1406.82 | J24: 1508.94 | K24: 17768.1
A25: Other Income | B25: 610.4 | C25: -135.03 | D25: -258.28 | E25: 382.26 | F25: -3449.21 | G25: -3505.16 | H25: 459.42 | I25: 865.23 | J25: 1444.42 | K25: 664.24
A26: Depreciation | B26: 1264.75 | C26: 1499.84 | D26: 1753.25 | E26: 2052.78 | F26: 2079.95 | G26: 2143.74 | H26: 2529.43 | I26: 2556.64 | J26: 2575.39 | K26: 2937.85
A27: Interest | B27: 399.8 | C27: 517.57 | D27: 555.25 | E27: 302.73 | F27: 141.43 | G27: 127.35 | H27: 172 | I27: 238.47 | J27: 231.36 | K27: 338.91
A28: Profit before tax | B28: 9047.87 | C28: 3478.98 | D28: 3810.2 | E28: 5009.59 | F28: 2799.37 | G28: 4481.32 | H28: 9408.43 | I28: 11087.89 | J28: 13752.13 | K28: 15118.88
A29: Tax | B29: 1211.57 | C29: 911.04 | D29: 600.88 | E29: 822.8 | F29: 514.69 | G29: 1075.5 | H29: 847.59 | I29: 1439.45 | J29: 2772.03 | K29: 3554.36
A30: Net profit | B30: 6964.37 | C30: 2095.7 | D30: 2665.42 | E30: 3764.93 | F30: 2903.82 | G30: 3272.73 | H30: 8473.58 | I30: 9576.38 | J30: 10929.04 | K30: 11479.42
A31: Dividend Amount | B31: 839.76 | C31: 479.86 | D31: 659.81 | E31: 959.72 | F31: 1799.48 | G31: 2399.3 | H31: 2759.2 | I31: 3239.06 | J31: 3838.88 | K31: 3838.88
A32: EBITDA | B32: =B30+B27+B26+B29 -> 9840.49 | C32: =C30+C27+C26+C29 -> 5024.15 | D32: =D30+D27+D26+D29 -> 5574.8 | E32: =E30+E27+E26+E29 -> 6943.24 | F32: =F30+F27+F26+F29 -> 5639.89 | G32: =G30+G27+G26+G29 -> 6619.32 | H32: =H30+H27+H26+H29 -> 12022.6 | I32: =I30+I27+I26+I29 -> 13810.94 | ... K32: =K30+K27+K26+K29 -> 18310.54
A40: Quarters
A41: Report Date | B41: 45291 | C41: 45382 | D41: 45473 | E41: 45565 | F41: 45657 | G41: 45747 | H41: 45838 | I41: 45930 | J41: 46022 | K41: 46112
A42: Sales | B42: 12380.7 | C42: 11982.9 | D42: 12652.75 | E42: 13291.39 | F42: 13675.46 | G42: 12958.84 | H42: 13851.4 | I42: 14478.31 | J42: 15520.54 | K42: 14611.79
A43: Expenses | B43: 8903.87 | C43: 8947.75 | D43: 9045.13 | E43: 9352.43 | F43: 9666.44 | G43: 9242.75 | H43: 9549.74 | I43: 9951.26 | J43: 10572.05 | K43: 10657.59
A44: Other Income | B44: 180.39 | C44: 504.3 | D44: 532.55 | E44: 354 | F44: 149.45 | G44: 251.19 | H44: -353.54 | I44: 469.92 | J44: 89.36 | K44: 458.5
A45: Depreciation | B45: 622.14 | C45: 650.36 | D45: 655.13 | E45: 625.91 | F45: 630.56 | G45: 663.79 | H45: 700.55 | I45: 729.5 | J45: 732.33 | K45: 775.47
A46: Interest | B46: 34.73 | C46: 73.57 | D46: 61.54 | E46: 69.17 | F46: 51.51 | G46: 49.14 | H46: 74.8 | I46: 99.86 | J46: 78.36 | K46: 85.89
A47: Profit before tax | B47: 3000.35 | C47: 2815.52 | D47: 3423.5 | E47: 3597.88 | F47: 3476.4 | G47: 3254.35 | H47: 3172.77 | I47: 4167.61 | J47: 4227.16 | K47: 3551.34
A48: Tax | B48: 432.32 | C48: 148.93 | D48: 552.25 | E48: 567.21 | F48: 558.86 | G48: 1093.71 | H48: 870.15 | I48: 1030.52 | J48: 826.07 | K48: 827.62
A49: Net profit | B49: 2523.75 | C49: 2654.58 | D49: 2835.62 | E49: 3040.16 | F49: 2903.38 | G49: 2149.88 | H49: 2278.63 | I49: 3117.95 | J49: 3368.81 | K49: 2714.03
A50: Operating Profit | B50: 3476.83 | C50: 3035.15 | D50: 3607.62 | E50: 3938.96 | F50: 4009.02 | G50: 3716.09 | H50: 4301.66 | I50: 4527.05 | J50: 4948.49 | K50: 3954.2
A55: BALANCE SHEET
A56: Report Date | B56: 42825 | C56: 43190 | D56: 43555 | E56: 43921 | F56: 44286 | G56: 44651 | H56: 45016 | I56: 45382 | J56: 45747 | K56: 46112
A57: Equity Share Capital | B57: 239.93 | C57: 239.93 | D57: 239.93 | E57: 239.93 | F57: 239.93 | G57: 239.93 | H57: 239.93 | I57: 239.93 | J57: 239.93 | K57: 239.93
A58: Reserves | B58: 36399.74 | C58: 38074.18 | D58: 41169.13 | E58: 45024.52 | F58: 46222.85 | G58: 47771.29 | H58: 55755.45 | I58: 63426.82 | J58: 71978.09 | K58: 83330.16
A59: Borrowings | B59: 9831.77 | C59: 10385.27 | D59: 10514.36 | E59: 8314.88 | F59: 3868.58 | G59: 1290.3 | H59: 6885.87 | I59: 3273.67 | J59: 2362.19 | K59: 4627.32
A60: Other Liabilities | B60: 14624.01 | C60: 15598.01 | D60: 12666.11 | E60: 14614.99 | F60: 17290.86 | G60: 20474.39 | H60: 17830.65 | I60: 18387.37 | J60: 17327.93 | K60: 20587.81
A61: Total | B61: 61095.45 | C61: 64297.39 | D61: 64589.53 | E61: 68194.32 | F61: 67622.22 | G61: 69775.91 | H61: 80711.9 | I61: 85327.79 | J61: 91908.14 | K61: 108785.22
A62: Net Block | B62: 17675.17 | C62: 18852.65 | D62: 21836.54 | E62: 22846.91 | F62: 21552.98 | G62: 22665.16 | H62: 24065.44 | I62: 23248.15 | J62: 22586.28 | K62: 34493.35
A63: Capital Work in Progress | B63: 2801.38 | C63: 2465.16 | D63: 1411.15 | E63: 1220.34 | F63: 1566.83 | G63: 1286.8 | H63: 4973.16 | I63: 5353.88 | J63: 6643.96 | K63: 1380.65
A64: Investments | B64: 1191.88 | C64: 7142.87 | D64: 7902.53 | E64: 10143.11 | F64: 9612.45 | G64: 12848.59 | H64: 14824.34 | I64: 15025.77 | J64: 18353.8 | K64: 24722.52
A65: Other Assets | B65: 39427.02 | C65: 35836.71 | D65: 33439.31 | E65: 33983.96 | F65: 34889.96 | G65: 32975.36 | H65: 36848.96 | I65: 41699.99 | J65: 44324.1 | K65: 48188.7
A66: Total | B66: 61095.45 | C66: 64297.39 | D66: 64589.53 | E66: 68194.32 | F66: 67622.22 | G66: 69775.91 | H66: 80711.9 | I66: 85327.79 | J66: 91908.14 | K66: 108785.22
A67: Receivables | B67: 7202.61 | C67: 7815.28 | D67: 8884.2 | E67: 9421.24 | F67: 9061.4 | G67: 10484.59 | H67: 11438.51 | I67: 11249.37 | J67: 13046.11 | K67: 15509.67
... A69: Cash & Bank | B69: 15140.84 | C69: 9929.38 | D69: 7275.6 | E69: 6487.55 | F69: 6445.51 | G69: 5033.35 | H69: 5770.29 | I69: 10520.68 | J69: 11331.62 | K69: 11603.08
A70: No. of Equity Shares | B70: 2399260815 | C70: 2399260815 | D70: 2399334970 | E70: 2399334970 | F70: 2399334970 | G70: 2399334970 | H70: 2399334970 | I70: 2399334970 | J70: 2399334970
A71: New Bonus Shares
A72: Face value | B72: 1 | C72: 1 | D72: 1 | E72: 1 | F72: 1 | G72: 1 | H72: 1 | I72: 1 | J72: 1 | K72: 1
A74: Other Assets | B74: =B65-SUM(B67:B69) -> 10250.76 | C74: =C65-SUM(C67:C69) -> 11211.36 | D74: =D65-SUM(D67:D69) -> 9393.53 | E74: =E65-SUM(E67:E69) -> 10200.18 | F74: =F65-SUM(F67:F69) -> 10386.03 | G74: =G65-SUM(G67:G69) -> 8532.29 | H74: =H65-SUM(H67:H69) -> 9127.11 | I74: =I65-SUM(I67:I69) -> 10061.65 | ... K74: =K65-SUM(K67:K69) -> 9583.02
A75: Total Assets | B75: =B61 -> 61095.45 | C75: =C61 -> 64297.39 | D75: =D61 -> 64589.53 | E75: =E61 -> 68194.32 | F75: =F61 -> 67622.22 | G75: =G61 -> 69775.91 | H75: =H61 -> 80711.9 | I75: =I61 -> 85327.79 | ... K75: =K61 -> 108785.22
A80: CASH FLOW:
A81: Report Date | B81: 42825 | C81: 43190 | D81: 43555 | E81: 43921 | F81: 44286 | G81: 44651 | H81: 45016 | I81: 45382 | J81: 45747 | K81: 46112
A82: Cash from Operating Activity | B82: 7082.21 | C82: 3907.15 | D82: 2196.45 | E82: 6554.77 | F82: 6170.37 | G82: 8984.54 | H82: 4959.33 | I82: 12134.98 | J82: 14072.09 | K82: 12419.18
A83: Cash from Investing Activity | B83: -4186.15 | C83: -3103.8 | D83: -310.08 | E83: -2225.32 | F83: 406.53 | G83: -5555.86 | H83: -7219.92 | I83: -762.9 | J83: -5183.15 | K83: -11344.05
A84: Cash from Financing Activity | B84: -2285.39 | C84: -1539.26 | D84: -2730.52 | E84: -5715.14 | F84: -5980.48 | G84: -5193.46 | H84: 2376.07 | I84: -6710.16 | J84: -7905.82 | K84: -2512.55
A85: Net Cash Flow | B85: 610.67 | C85: -735.91 | D85: -844.15 | E85: -1385.69 | F85: 596.42 | G85: -1764.78 | H85: 115.48 | I85: 4661.92 | J85: 983.12 | K85: -1437.42
A90: PRICE: | B90: 688.15 | C90: 495.1 | D90: 478.85 | E90: 352.3 | F90: 597.8 | G90: 914.75 | H90: 983.1 | I90: 1620.55 | J90: 1734.7 | K90: 1757.2
A92: DERIVED:
A93: Adjusted Equity Shares in Cr | B93: 239.93 | C93: 239.93 | D93: 239.93 | E93: 239.93 | F93: 239.93 | G93: 239.93 | H93: 239.93 | I93: 239.93 | J93: 239.93 | K93: 239.93

Sheet Ratio Analysis
B2: ="Ratio Analysis - "&UPDATE -> Ratio Analysis - SUN PHARMACEUTICAL INDUSTRIES LTD
B3: Years | C3: ='Data Sheet'!B16 -> 42825 | D3: ='Data Sheet'!C16 -> 43190 | E3: ='Data Sheet'!D16 -> 43555 | F3: ='Data Sheet'!E16 -> 43921 | G3: ='Data Sheet'!F16 -> 44286 | H3: ='Data Sheet'!G16 -> 44651 | I3: ='Data Sheet'!H16 -> 45016 | J3: ='Data Sheet'!I16 -> 45382 | ... L3: ='Data Sheet'!K16 -> 46112 | M3: Trend | N3: Mean | O3: Median
B5: SalesGrowth | D5: =IFERROR(HistoricalFS!D7,0) -> -0.16115362 | E5: =IFERROR(HistoricalFS!E7,0) -> 0.097263213 | F5: =IFERROR(HistoricalFS!F7,0) -> 0.12975991 | G5: =IFERROR(HistoricalFS!G7,0) -> 0.020118462 | H5: =IFERROR(HistoricalFS!H7,0) -> 0.15392944 | I5: =IFERROR(HistoricalFS!I7,0) -> 0.13533201 | J5: =IFERROR(HistoricalFS!J7,0) -> 0.10507232 | K5: =IFERROR(HistoricalFS!K7,0) -> 0.084161961 | L5: =IFERROR(HistoricalFS!L7,0) -> 0.11190138 | N5: =IFERROR(AVERAGE(D5:L5),0) -> 0.075153898 | O5: =IFERROR(MEDIAN(C5:L5),0) -> 0.10507232
B6: EBITDA Growth | D6: =IFERROR(HistoricalFS!D18/HistoricalFS!C18-1,0) -> -0.44254515 | E6: =IFERROR(HistoricalFS!E18/HistoricalFS!D18-1,0) -> 0.1323929 | F6: =IFERROR(HistoricalFS!F18/HistoricalFS!E18-1,0) -> 0.095007355 | G6: =IFERROR(HistoricalFS!G18/HistoricalFS!F18-1,0) -> 0.21296779 | H6: =IFERROR(HistoricalFS!H18/HistoricalFS!G18-1,0) -> 0.21105294 | I6: =IFERROR(HistoricalFS!I18/HistoricalFS!H18-1,0) -> 0.13578947 | J6: =IFERROR(HistoricalFS!J18/HistoricalFS!I18-1,0) -> 0.11736295 | K6: =IFERROR(HistoricalFS!K18/HistoricalFS!J18-1,0) -> 0.16106368 | L6: =IFERROR(HistoricalFS!L18/HistoricalFS!K18-1,0) -> 0.17314148 | N6: =IFERROR(AVERAGE(D6:L6),0) -> 0.08847038 | O6: =IFERROR(MEDIAN(C6:L6),0) -> 0.13578947
B7: EBIT Growth | D7: =IFERROR(HistoricalFS!D32/HistoricalFS!C32-1,0) -> -0.61549182 | E7: =IFERROR(HistoricalFS!E32/HistoricalFS!D32-1,0) -> 0.095206066 | F7: =IFERROR(HistoricalFS!F32/HistoricalFS!E32-1,0) -> 0.314784 | G7: =IFERROR(HistoricalFS!G32/HistoricalFS!F32-1,0) -> -0.44119778 | H7: =IFERROR(HistoricalFS!H32/HistoricalFS!G32-1,0) -> 0.60083162 | I7: =IFERROR(HistoricalFS!I32/HistoricalFS!H32-1,0) -> 1.0994774 | J7: =IFERROR(HistoricalFS!J32/HistoricalFS!I32-1,0) -> 0.17850587 | K7: =IFERROR(HistoricalFS!K32/HistoricalFS!J32-1,0) -> 0.24028377 | L7: =IFERROR(HistoricalFS!L32/HistoricalFS!K32-1,0) -> 0.099384604 | N7: =IFERROR(AVERAGE(D7:L7),0) -> 0.17464263 | O7: =IFERROR(MEDIAN(C7:L7),0) -> 0.17850587
B8: NetProfit Growth | D8: =IFERROR(HistoricalFS!D38/HistoricalFS!C38-1,0) -> -0.67230198 | E8: =IFERROR(HistoricalFS!E38/HistoricalFS!D38-1,0) -> 0.2497644 | F8: =IFERROR(HistoricalFS!F38/HistoricalFS!E38-1,0) -> 0.30457231 | G8: =IFERROR(HistoricalFS!G38/HistoricalFS!F38-1,0) -> -0.45431225 | H8: =IFERROR(HistoricalFS!H38/HistoricalFS!G38-1,0) -> 0.4907208 | I8: =IFERROR(HistoricalFS!I38/HistoricalFS!H38-1,0) -> 1.5135914 | J8: =IFERROR(HistoricalFS!J38/HistoricalFS!I38-1,0) -> 0.12704361 | K8: =IFERROR(HistoricalFS!K38/HistoricalFS!J38-1,0) -> 0.13801817 | L8: =IFERROR(HistoricalFS!L38/HistoricalFS!K38-1,0) -> 0.05322538 | N8: =IFERROR(AVERAGE(D8:L8),0) -> 0.19448021 | O8: =IFERROR(MEDIAN(C8:L8),0) -> 0.13801817
B9: Dividend Growth | D9: =IFERROR(HistoricalFS!D46/HistoricalFS!C46-1,0) -> -0.42857483 | E9: =IFERROR(HistoricalFS!E46/HistoricalFS!D46-1,0) -> 0.37500521 | F9: =IFERROR(HistoricalFS!F46/HistoricalFS!E46-1,0) -> 0.45453994 | G9: =IFERROR(HistoricalFS!G46/HistoricalFS!F46-1,0) -> 0.87500521 | H9: =IFERROR(HistoricalFS!H46/HistoricalFS!G46-1,0) -> 0.33332963 | I9: =IFERROR(HistoricalFS!I46/HistoricalFS!H46-1,0) -> 0.15000208 | J9: =IFERROR(HistoricalFS!J46/HistoricalFS!I46-1,0) -> 0.17391273 | K9: =IFERROR(HistoricalFS!K46/HistoricalFS!J46-1,0) -> 0.18518336 | L9: =IFERROR(HistoricalFS!L46/HistoricalFS!K46-1,0) -> 0 | N9: =IFERROR(AVERAGE(D9:L9),0) -> 0.23537815 | O9: =IFERROR(MEDIAN(C9:L9),0) -> 0.18518336
B11: Gross Margin | C11: =IFERROR(HistoricalFS!C13,0) -> 0.50815841 | D11: =IFERROR(HistoricalFS!D13,0) -> 0.42694 | E11: =IFERROR(HistoricalFS!E13,0) -> 0.4380231 | F11: =IFERROR(HistoricalFS!F13,0) -> 0.45474869 | G11: =IFERROR(HistoricalFS!G13,0) -> 0.46554704 | H11: =IFERROR(HistoricalFS!H13,0) -> 0.47649393 | I11: =IFERROR(HistoricalFS!I13,0) -> 0.50496358 | J11: =IFERROR(HistoricalFS!J13,0) -> 0.52493677 | ... L11: =IFERROR(HistoricalFS!L13,0) -> 0.60722308 | N11: =IFERROR(AVERAGE(C11:L11),0) -> 0.49556686 | O11: =IFERROR(MEDIAN(C11:L11),0) -> 0.49072876
B12: EBITDA Margin | C12: =IFERROR(HistoricalFS!C19,0) -> 0.31990244 | D12: =IFERROR(HistoricalFS!D19,0) -> 0.21259097 | E12: =IFERROR(HistoricalFS!E19,0) -> 0.21939723 | F12: =IFERROR(HistoricalFS!F19,0) -> 0.21264834 | G12: =IFERROR(HistoricalFS!G19,0) -> 0.25284867 | H12: =IFERROR(HistoricalFS!H19,0) -> 0.26536555 | I12: =IFERROR(HistoricalFS!I19,0) -> 0.26547247 | J12: =IFERROR(HistoricalFS!J19,0) -> 0.26842506 | ... L12: =IFERROR(HistoricalFS!L19,0) -> 0.30329766 | N12: =IFERROR(AVERAGE(C12:L12),0) -> 0.26074134 | O12: =IFERROR(MEDIAN(C12:L12),0) -> 0.26541901
B13: EBIT Margin | C13: =IFERROR((HistoricalFS!C18-HistoricalFS!C26)/HistoricalFS!C6,0) -> 0.27985138 | D13: =IFERROR((HistoricalFS!D18-HistoricalFS!D26)/HistoricalFS!D6,0) -> 0.15597071 | E13: =IFERROR((HistoricalFS!E18-HistoricalFS!E26)/HistoricalFS!E6,0) -> 0.15907742 | F13: =IFERROR((HistoricalFS!F18-HistoricalFS!F26)/HistoricalFS!F6,0) -> 0.15013506 | G13: =IFERROR((HistoricalFS!G18-HistoricalFS!G26)/HistoricalFS!G6,0) -> 0.19075716 | H13: =IFERROR((HistoricalFS!H18-HistoricalFS!H26)/HistoricalFS!H6,0) -> 0.20990653 | I13: =IFERROR((HistoricalFS!I18-HistoricalFS!I26)/HistoricalFS!I6,0) -> 0.20783568 | J13: =IFERROR((HistoricalFS!J18-HistoricalFS!J26)/HistoricalFS!J6,0) -> 0.21570741 | ... L13: =IFERROR((HistoricalFS!L18-HistoricalFS!L26)/HistoricalFS!L6,0) -> 0.25304539 | N13: =IFERROR(AVERAGE(C13:L13),0) -> 0.20607699 | O13: =IFERROR(MEDIAN(C13:L13),0) -> 0.20887111
B14: EBT Margin | C14: =IFERROR(HistoricalFS!C33,0) -> 0.28652049 | D14: =IFERROR(HistoricalFS!D33,0) -> 0.1313345 | E14: =IFERROR(HistoricalFS!E33,0) -> 0.13108827 | F14: =IFERROR(HistoricalFS!F33,0) -> 0.15255699 | G14: =IFERROR(HistoricalFS!G33,0) -> 0.083567923 | H14: =IFERROR(HistoricalFS!H33,0) -> 0.11593272 | I14: =IFERROR(HistoricalFS!I33,0) -> 0.21438497 | J14: =IFERROR(HistoricalFS!J33,0) -> 0.22863114 | ... L14: =IFERROR(HistoricalFS!L33,0) -> 0.2586102 | N14: =IFERROR(AVERAGE(C14:L14),0) -> 0.18641817 | O14: =IFERROR(MEDIAN(C14:L14),0) -> 0.18347098
B15: Net Profit Margin | C15: =IFERROR(HistoricalFS!C39,0) -> 0.24815349 | D15: =IFERROR(HistoricalFS!D39,0) -> 0.096941954 | E15: =IFERROR(HistoricalFS!E39,0) -> 0.11041526 | F15: =IFERROR(HistoricalFS!F39,0) -> 0.12750027 | G15: =IFERROR(HistoricalFS!G39,0) -> 0.06820319 | H15: =IFERROR(HistoricalFS!H39,0) -> 0.088109299 | I15: =IFERROR(HistoricalFS!I39,0) -> 0.19507138 | J15: =IFERROR(HistoricalFS!J39,0) -> 0.19894983 | ... L15: =IFERROR(HistoricalFS!L39,0) -> 0.19781246 | N15: =IFERROR(AVERAGE(C15:L15),0) -> 0.15399899 | O15: =IFERROR(MEDIAN(C15:L15),0) -> 0.16128582
O16: =IFERROR(MEDIAN(C16:L16),0) -> 0
B17: SalesExp% Sales | C17: =IFERROR(HistoricalFS!C16,0) -> 0.18825597 | D17: =IFERROR(HistoricalFS!D16,0) -> 0.21434903 | E17: =IFERROR(HistoricalFS!E16,0) -> 0.21862587 | F17: =IFERROR(HistoricalFS!F16,0) -> 0.24210034 | G17: =IFERROR(HistoricalFS!G16,0) -> 0.21269838 | H17: =IFERROR(HistoricalFS!H16,0) -> 0.21112838 | I17: =IFERROR(HistoricalFS!I16,0) -> 0.23949111 | J17: =IFERROR(HistoricalFS!J16,0) -> 0.25651171 | ... L17: =IFERROR(HistoricalFS!L16,0) -> 0.30392542 | N17: =IFERROR(AVERAGE(C17:L17),0) -> 0.23482552 | O17: =IFERROR(MEDIAN(C17:L17),0) -> 0.22905849
B18: Deprn%Sales | C18: =IFERROR(HistoricalFS!C27,0) -> 0.04005106 | D18: =IFERROR(HistoricalFS!D27,0) -> 0.056620256 | E18: =IFERROR(HistoricalFS!E27,0) -> 0.060319804 | F18: =IFERROR(HistoricalFS!F27,0) -> 0.062513285 | G18: =IFERROR(HistoricalFS!G27,0) -> 0.062091507 | H18: =IFERROR(HistoricalFS!H27,0) -> 0.055459017 | I18: =IFERROR(HistoricalFS!I27,0) -> 0.057636796 | J18: =IFERROR(HistoricalFS!J27,0) -> 0.052717651 | ... L18: =IFERROR(HistoricalFS!L27,0) -> 0.050252266 | N18: =IFERROR(AVERAGE(C18:L18),0) -> 0.054664351 | O18: =IFERROR(MEDIAN(C18:L18),0) -> 0.056039636
B19: OprIncome%Sales | C19: =C13 -> 0.27985138 | D19: =D13 -> 0.15597071 | E19: =E13 -> 0.15907742 | F19: =F13 -> 0.15013506 | G19: =G13 -> 0.19075716 | H19: =H13 -> 0.20990653 | I19: =I13 -> 0.20783568 | J19: =J13 -> 0.21570741 | ... L19: =L13 -> 0.25304539 | N19: =IFERROR(AVERAGE(C19:L19),0) -> 0.20607699 | O19: =IFERROR(MEDIAN(C19:L19),0) -> 0.20887111
O20: =IFERROR(MEDIAN(C20:L20),0) -> 0
B21: Return on Cap Emp | C21: =IFERROR((HistoricalFS!C29)/(SUM(HistoricalFS!C53:C55)),0) -> 0.19016562 | D21: =IFERROR((HistoricalFS!D29)/(SUM(HistoricalFS!D53:D55)),0) -> 0.084838452 | E21: =IFERROR((HistoricalFS!E29)/(SUM(HistoricalFS!E53:E55)),0) -> 0.089049026 | F21: =IFERROR((HistoricalFS!F29)/(SUM(HistoricalFS!F53:F55)),0) -> 0.092014215 | G21: =IFERROR((HistoricalFS!G29)/(SUM(HistoricalFS!G53:G55)),0) -> 0.12695882 | H21: =IFERROR((HistoricalFS!H29)/(SUM(HistoricalFS!H53:H55)),0) -> 0.16457566 | I21: =IFERROR((HistoricalFS!I29)/(SUM(HistoricalFS!I53:I55)),0) -> 0.14505135 | J21: =IFERROR((HistoricalFS!J29)/(SUM(HistoricalFS!J53:J55)),0) -> 0.15627524 | ... L21: =IFERROR((HistoricalFS!L29)/(SUM(HistoricalFS!L53:L55)),0) -> 0.16773225 | N21: =IFERROR(AVERAGE(C21:L21),0) -> 0.13847893 | O21: =IFERROR(MEDIAN(C21:L21),0) -> 0.15066329
B22: Retained Earn % | C22: =IFERROR(HistoricalFS!C49,0) -> 1.1071628 | D22: =IFERROR(HistoricalFS!D49,0) -> 1.1868657 | E22: =IFERROR(HistoricalFS!E49,0) -> 1.2055918 | F22: =IFERROR(HistoricalFS!F49,0) -> 1.2292257 | G22: =IFERROR(HistoricalFS!G49,0) -> 1.7876289 | H22: =IFERROR(HistoricalFS!H49,0) -> 1.7044706 | I22: =IFERROR(HistoricalFS!I49,0) -> 1.3223048 | J22: =IFERROR(HistoricalFS!J49,0) -> 1.3357082 | ... L22: =IFERROR(HistoricalFS!L49,0) -> 1.3319533 | N22: =IFERROR(AVERAGE(C22:L22),0) -> 1.3560533 | O22: =IFERROR(MEDIAN(C22:L22),0) -> 1.327129
B23: Return on Equity% | C23: =IFERROR(HistoricalFS!C38/SUM(HistoricalFS!C53:C54),0) -> 0.21387474 | D23: =IFERROR(HistoricalFS!D38/SUM(HistoricalFS!D53:D54),0) -> 0.06702335 | E23: =IFERROR(HistoricalFS!E38/SUM(HistoricalFS!E53:E54),0) -> 0.077502846 | F23: =IFERROR(HistoricalFS!F38/SUM(HistoricalFS!F53:F54),0) -> 0.092496208 | G23: =IFERROR(HistoricalFS!G38/SUM(HistoricalFS!G53:G54),0) -> 0.049172262 | H23: =IFERROR(HistoricalFS!H38/SUM(HistoricalFS!H53:H54),0) -> 0.070938002 | I23: =IFERROR(HistoricalFS!I38/SUM(HistoricalFS!I53:I54),0) -> 0.15288476 | J23: =IFERROR(HistoricalFS!J38/SUM(HistoricalFS!J53:J54),0) -> 0.15154598 | ... L23: =IFERROR(HistoricalFS!L38/SUM(HistoricalFS!L53:L54),0) -> 0.13838109 | N23: =IFERROR(AVERAGE(C23:L23),0) -> 0.11658602 | O23: =IFERROR(MEDIAN(C23:L23),0) -> 0.11543865
B24: Self Sust Growth Rate | C24: =IFERROR(C22*C23,0) -> 0.23679416 | D24: =IFERROR(D22*D23,0) -> 0.079547718 | E24: =IFERROR(E22*E23,0) -> 0.093436799 | F24: =IFERROR(F22*F23,0) -> 0.11369872 | G24: =IFERROR(G22*G23,0) -> 0.087901757 | H24: =IFERROR(H22*H23,0) -> 0.12091174 | I24: =IFERROR(I22*I23,0) -> 0.20216025 | J24: =IFERROR(J22*J23,0) -> 0.2024212 | ... L24: =IFERROR(L22*L23,0) -> 0.18431714 | N24: =IFERROR(AVERAGE(C24:L24),0) -> 0.15263873 | O24: =IFERROR(MEDIAN(C24:L24),0) -> 0.15261444
B25: Interest Cov Ratio | C25: =IFERROR((HistoricalFS!C18-HistoricalFS!C26)/HistoricalFS!C23,0) -> 22.104227 | D25: =IFERROR((HistoricalFS!D18-HistoricalFS!D26)/HistoricalFS!D23,0) -> 7.9826497 | E25: =IFERROR((HistoricalFS!E18-HistoricalFS!E26)/HistoricalFS!E23,0) -> 8.327294 | F25: =IFERROR((HistoricalFS!F18-HistoricalFS!F26)/HistoricalFS!F23,0) -> 16.285337 | G25: =IFERROR((HistoricalFS!G18-HistoricalFS!G26)/HistoricalFS!G23,0) -> 45.181433 | H25: =IFERROR((HistoricalFS!H18-HistoricalFS!H26)/HistoricalFS!H23,0) -> 63.712839 | I25: =IFERROR((HistoricalFS!I18-HistoricalFS!I26)/HistoricalFS!I23,0) -> 53.029128 | J25: =IFERROR((HistoricalFS!J18-HistoricalFS!J26)/HistoricalFS!J23,0) -> 43.867698 | ... L25: =IFERROR((HistoricalFS!L18-HistoricalFS!L26)/HistoricalFS!L23,0) -> 43.650379 | N25: =IFERROR(AVERAGE(C25:L25),0) -> 35.833821 | O25: =IFERROR(MEDIAN(C25:L25),0) -> 43.759039
O26: =IFERROR(MEDIAN(C26:L26),0) -> 0
B27: Debt Turnover Ratio | C27: =IFERROR(HistoricalFS!C6/HistoricalFS!C65,0) -> 4.3843051 | D27: =IFERROR(HistoricalFS!D6/HistoricalFS!D65,0) -> 3.3894448 | E27: =IFERROR(HistoricalFS!E6/HistoricalFS!E65,0) -> 3.2716407 | F27: =IFERROR(HistoricalFS!F6/HistoricalFS!F65,0) -> 3.4854754 | G27: =IFERROR(HistoricalFS!G6/HistoricalFS!G65,0) -> 3.6967952 | H27: =IFERROR(HistoricalFS!H6/HistoricalFS!H65,0) -> 3.6867908 | I27: =IFERROR(HistoricalFS!I6/HistoricalFS!I65,0) -> 3.8366605 | J27: =IFERROR(HistoricalFS!J6/HistoricalFS!J65,0) -> 4.3110725 | ... L27: =IFERROR(HistoricalFS!L6/HistoricalFS!L65,0) -> 3.7693929 | N27: =IFERROR(AVERAGE(C27:L27),0) -> 3.7861779 | O27: =IFERROR(MEDIAN(C27:L27),0) -> 3.733094
B28: Creditor Turnover Ratio | C28: =IFERROR(HistoricalFS!C6/HistoricalFS!C56,0) -> 2.1593557 | D28: =IFERROR(HistoricalFS!D6/HistoricalFS!D56,0) -> 1.6982589 | E28: =IFERROR(HistoricalFS!E6/HistoricalFS!E56,0) -> 2.294778 | F28: =IFERROR(HistoricalFS!F6/HistoricalFS!F56,0) -> 2.246837 | G28: =IFERROR(HistoricalFS!G6/HistoricalFS!G56,0) -> 1.9373322 | H28: =IFERROR(HistoricalFS!H6/HistoricalFS!H56,0) -> 1.8879434 | I28: =IFERROR(HistoricalFS!I6/HistoricalFS!I56,0) -> 2.4612496 | J28: =IFERROR(HistoricalFS!J6/HistoricalFS!J56,0) -> 2.6375088 | ... L28: =IFERROR(HistoricalFS!L6/HistoricalFS!L56,0) -> 2.8396435 | N28: =IFERROR(AVERAGE(C28:L28),0) -> 2.3197225 | O28: =IFERROR(MEDIAN(C28:L28),0) -> 2.2708075
B29: Invt Turnover | C29: =HistoricalFS!C6/HistoricalFS!C66 -> 4.6215891 | D29: =HistoricalFS!D6/HistoricalFS!D66 -> 3.8498261 | E29: =HistoricalFS!E6/HistoricalFS!E66 -> 3.6857702 | F29: =HistoricalFS!F6/HistoricalFS!F66 -> 4.1698466 | G29: =HistoricalFS!G6/HistoricalFS!G66 -> 3.7232484 | H29: =HistoricalFS!H6/HistoricalFS!H66 -> 4.3309722 | I29: =HistoricalFS!I6/HistoricalFS!I66 -> 4.1744004 | J29: =HistoricalFS!J6/HistoricalFS!J66 -> 4.9144127 | ... L29: =HistoricalFS!L6/HistoricalFS!L66 -> 5.0867829 | N29: =IFERROR(AVERAGE(C29:L29),0) -> 4.3689793 | O29: =IFERROR(MEDIAN(C29:L29),0) -> 4.2526863
B30: Fixed Asset Turnover | C30: =IFERROR(HistoricalFS!C6/HistoricalFS!C59,0) -> 1.7865989 | D30: =IFERROR(HistoricalFS!D6/HistoricalFS!D59,0) -> 1.4050789 | E30: =IFERROR(HistoricalFS!E6/HistoricalFS!E59,0) -> 1.3310676 | F30: =IFERROR(HistoricalFS!F6/HistoricalFS!F59,0) -> 1.4372841 | G30: =IFERROR(HistoricalFS!G6/HistoricalFS!G59,0) -> 1.5542231 | H30: =IFERROR(HistoricalFS!H6/HistoricalFS!H59,0) -> 1.7054585 | I30: =IFERROR(HistoricalFS!I6/HistoricalFS!I59,0) -> 1.8235977 | J30: =IFERROR(HistoricalFS!J6/HistoricalFS!J59,0) -> 2.086052 | ... L30: =IFERROR(HistoricalFS!L6/HistoricalFS!L59,0) -> 1.6948786 | N30: =IFERROR(AVERAGE(C30:L30),0) -> 1.7152132 | O30: =IFERROR(MEDIAN(C30:L30),0) -> 1.7001685
B31: Capital Turnover Ratio | C31: =IFERROR(HistoricalFS!C6/SUM(HistoricalFS!C53:C54),0) -> 0.86186475 | D31: =IFERROR(HistoricalFS!D6/SUM(HistoricalFS!D53:D54),0) -> 0.6913761 | E31: =IFERROR(HistoricalFS!E6/SUM(HistoricalFS!E53:E54),0) -> 0.70192151 | F31: =IFERROR(HistoricalFS!F6/SUM(HistoricalFS!F53:F54),0) -> 0.72545894 | G31: =IFERROR(HistoricalFS!G6/SUM(HistoricalFS!G53:G54),0) -> 0.72096719 | H31: =IFERROR(HistoricalFS!H6/SUM(HistoricalFS!H53:H54),0) -> 0.80511368 | I31: =IFERROR(HistoricalFS!I6/SUM(HistoricalFS!I53:I54),0) -> 0.78373752 | J31: =IFERROR(HistoricalFS!J6/SUM(HistoricalFS!J53:J54),0) -> 0.76172963 | ... L31: =IFERROR(HistoricalFS!L6/SUM(HistoricalFS!L53:L54),0) -> 0.69955698 | N31: =IFERROR(AVERAGE(C31:L31),0) -> 0.74797778 | O31: =IFERROR(MEDIAN(C31:L31),0) -> 0.72675524
O32: =IFERROR(MEDIAN(C32:L32),0) -> 0
B33: (in days) | O33: =IFERROR(MEDIAN(C33:L33),0) -> 0
B34: Debtor Days | C34: =IFERROR(365/C27,0) -> 83.251505 | D34: =IFERROR(365/D27,0) -> 107.68725 | E34: =IFERROR(365/E27,0) -> 111.56482 | F34: =IFERROR(365/F27,0) -> 104.72029 | G34: =IFERROR(365/G27,0) -> 98.734169 | H34: =IFERROR(365/H27,0) -> 99.002091 | I34: =IFERROR(365/I27,0) -> 95.134817 | J34: =IFERROR(365/J27,0) -> 84.665706 | ... L34: =IFERROR(365/L27,0) -> 96.832569 | N34: =IFERROR(AVERAGE(C34:L34),0) -> 97.215944 | O34: =IFERROR(MEDIAN(C34:L34),0) -> 97.783369
B35: Payable Days | C35: =IFERROR(365/C28,0) -> 169.0319 | D35: =IFERROR(365/D28,0) -> 214.926 | E35: =IFERROR(365/E28,0) -> 159.05678 | F35: =IFERROR(365/F28,0) -> 162.45059 | G35: =IFERROR(365/G28,0) -> 188.40341 | H35: =IFERROR(365/H28,0) -> 193.33206 | I35: =IFERROR(365/I28,0) -> 148.29865 | J35: =IFERROR(365/J28,0) -> 138.38816 | ... L35: =IFERROR(365/L28,0) -> 128.53726 | N35: =IFERROR(AVERAGE(C35:L35),0) -> 162.27155 | O35: =IFERROR(MEDIAN(C35:L35),0) -> 160.75369
B36: Invt Days | C36: =IFERROR(365/C29,0) -> 78.977164 | D36: =IFERROR(365/D29,0) -> 94.809477 | E36: =IFERROR(365/E29,0) -> 99.029506 | F36: =IFERROR(365/F29,0) -> 87.533197 | G36: =IFERROR(365/G29,0) -> 98.032676 | H36: =IFERROR(365/H29,0) -> 84.276689 | I36: =IFERROR(365/I29,0) -> 87.437707 | J36: =IFERROR(365/J29,0) -> 74.271336 | ... L36: =IFERROR(365/L29,0) -> 71.754586 | N36: =IFERROR(AVERAGE(C36:L36),0) -> 84.723163 | O36: =IFERROR(MEDIAN(C36:L36),0) -> 85.857198
B37: Cash Conversion Cycle | C37: =SUM(C34,C36-C35) -> -6.8032287 | D37: =SUM(D34,D36-D35) -> -12.429268 | E37: =SUM(E34,E36-E35) -> 51.537542 | F37: =SUM(F34,F36-F35) -> 29.802896 | G37: =SUM(G34,G36-G35) -> 8.3634315 | H37: =SUM(H34,H36-H35) -> -10.053284 | I37: =SUM(I34,I36-I35) -> 34.273871 | J37: =SUM(J34,J36-J35) -> 20.548878 | ... L37: =SUM(L34,L36-L35) -> 40.049891 | N37: =IFERROR(AVERAGE(C37:L37),0) -> 19.667559 | O37: =IFERROR(MEDIAN(C37:L37),0) -> 25.175887
O38: =IFERROR(MEDIAN(C38:L38),0) -> 0
B39: CFO/Sales | C39: =IFERROR(HistoricalFS!C115/HistoricalFS!C6,0) -> 0.22427359 | D39: =IFERROR(HistoricalFS!D115/HistoricalFS!D6,0) -> 0.14749829 | E39: =IFERROR(HistoricalFS!E115/HistoricalFS!E6,0) -> 0.075567908 | F39: =IFERROR(HistoricalFS!F115/HistoricalFS!F6,0) -> 0.19961233 | G39: =IFERROR(HistoricalFS!G115/HistoricalFS!G6,0) -> 0.18420038 | H39: =IFERROR(HistoricalFS!H115/HistoricalFS!H6,0) -> 0.23243199 | I39: =IFERROR(HistoricalFS!I115/HistoricalFS!I6,0) -> 0.11300565 | J39: =IFERROR(HistoricalFS!J115/HistoricalFS!J6,0) -> 0.25022202 | ... L39: =IFERROR(HistoricalFS!L115/HistoricalFS!L6,0) -> 0.21243152 | N39: =IFERROR(AVERAGE(C39:L39),0) -> 0.19068836 | O39: =IFERROR(MEDIAN(C39:L39),0) -> 0.20602193
B40: CFO/Total Assets | C40: =IFERROR(HistoricalFS!C115/HistoricalFS!C70,0) -> 0.11592042 | D40: =IFERROR(HistoricalFS!D115/HistoricalFS!D70,0) -> 0.060766852 | E40: =IFERROR(HistoricalFS!E115/HistoricalFS!E70,0) -> 0.034006286 | F40: =IFERROR(HistoricalFS!F115/HistoricalFS!F70,0) -> 0.096119002 | G40: =IFERROR(HistoricalFS!G115/HistoricalFS!G70,0) -> 0.09124767 | H40: =IFERROR(HistoricalFS!H115/HistoricalFS!H70,0) -> 0.12876278 | I40: =IFERROR(HistoricalFS!I115/HistoricalFS!I70,0) -> 0.061444843 | J40: =IFERROR(HistoricalFS!J115/HistoricalFS!J70,0) -> 0.14221604 | ... L40: =IFERROR(HistoricalFS!L115/HistoricalFS!L70,0) -> 0.11416238 | N40: =IFERROR(AVERAGE(C40:L40),0) -> 0.099775664 | O40: =IFERROR(MEDIAN(C40:L40),0) -> 0.10514069
B41: CFO/Total Debt | C41: =IFERROR(HistoricalFS!C115/HistoricalFS!C55,0) -> 0.72033927 | D41: =IFERROR(HistoricalFS!D115/HistoricalFS!D55,0) -> 0.37622036 | E41: =IFERROR(HistoricalFS!E115/HistoricalFS!E55,0) -> 0.20890002 | F41: =IFERROR(HistoricalFS!F115/HistoricalFS!F55,0) -> 0.78831805 | G41: =IFERROR(HistoricalFS!G115/HistoricalFS!G55,0) -> 1.5949961 | H41: =IFERROR(HistoricalFS!H115/HistoricalFS!H55,0) -> 6.9631404 | I41: =IFERROR(HistoricalFS!I115/HistoricalFS!I55,0) -> 0.72021836 | J41: =IFERROR(HistoricalFS!J115/HistoricalFS!J55,0) -> 3.7068428 | ... L41: =IFERROR(HistoricalFS!L115/HistoricalFS!L55,0) -> 2.6838818 | N41: =IFERROR(AVERAGE(C41:L41),0) -> 2.3720079 | O41: =IFERROR(MEDIAN(C41:L41),0) -> 1.1916571

Sheet CashFlow Data
C2: 42795 | D2: 43160 | E2: 43525 | F2: 43891 | G2: 44256 | H2: 44621 | I2: 44986 | J2: 45352 | K2: 45717 | L2: 46082
B3: Cash from Operating Activity - | C3: 7082 | D3: 3907 | E3: 2196 | F3: 6555 | G3: 6170 | H3: 8985 | I3: 4959 | J3: 12135 | K3: 14072 | L3: 12419
B4: Profit from operations | C4: 9549 | D4: 4861 | E4: 5779 | F4: 7002 | G4: 4609 | H4: 6456 | I4: 12131 | J4: 12642 | K4: 14872 | L4: 16001
B5: Receivables | C5: -293 | D5: -773 | E5: -858 | F5: -374 | G5: 94 | H5: -1342 | I5: -953 | J5: 353 | K5: -1602 | L5: -2009
B6: Inventory | C6: -345 | D6: -4 | E6: -709 | F6: 257 | G6: -1080 | H6: 307 | I6: -1202 | J6: 599 | K6: -184 | L6: -52
B7: Payables | C7: 735 | D7: 383 | E7: -854 | F7: -210 | G7: 381 | H7: 370 | I7: 1182 | J7: 250 | K7: 528 | L7: 1057
B8: Loans Advances | C8: 0 | D8: 0 | E8: 0 | F8: 0 | G8: 0 | H8: 0 | I8: 0 | J8: 0 | K8: 0 | L8: 0
B9: Other WC items | C9: -506 | D9: 182 | E9: -275 | F9: 1226 | G9: 3169 | H9: 2224 | I9: -4689 | J9: -139 | K9: 934 | L9: -264
B10: Working capital changes | C10: -409 | D10: -212 | E10: -2696 | F10: 899 | G10: 2564 | H10: 1559 | I10: -5662 | J10: 1062 | K10: -324 | L10: -1268
B11: Direct taxes | C11: -2057 | D11: -742 | E11: -886 | F11: -1346 | G11: -1003 | H11: 969 | I11: -1510 | J11: -1569 | K11: -477 | L11: -2314
B12: Cash from Investing Activity - | C12: -4186 | D12: -3104 | E12: -310 | F12: -2225 | G12: 407 | H12: -5556 | I12: -7220 | J12: -763 | K12: -5183 | L12: -11344
B13: Fixed assets purchased | C13: -3693 | D13: -1961 | E13: -3213 | F13: -1542 | G13: -1170 | H13: -1495 | I13: -2086 | J13: -2202 | K13: -2129 | L13: -3609
B14: Fixed assets sold | C14: 102 | D14: 66 | E14: 50 | F14: 92 | G14: 97 | H14: 61 | I14: 21 | J14: 31 | K14: 61 | L14: 96
... B33: CFO/OP | C33: 0.9 | D33: 0.83 | E33: 0.48 | F33: 1.13 | G33: 0.85 | H33: 0.78 | I33: 0.56 | J33: 1.05 | K33: 0.96 | L33: 0.83

Sheet Forecast
B1: Tata Motors
B2: Year Weight | C2: Year | D2: Sales | E2: Sales Growth
B3: 1 | C3: 2015 | D3: 263159
B4: =B3+1 -> 2 | C4: =C3+1 -> 2016 | D4: 273046 | E4: =D4/D3-1 -> 0.037570442
B5: =B4+1 -> 3 | C5: =C4+1 -> 2017 | D5: 269693 | E5: =D5/D4-1 -> -0.012279982
B6: =B5+1 -> 4 | C6: =C5+1 -> 2018 | D6: 291550 | E6: =D6/D5-1 -> 0.081044002
B7: =B6+1 -> 5 | C7: =C6+1 -> 2019 | D7: 301938 | E7: =D7/D6-1 -> 0.035630252
B8: =B7+1 -> 6 | C8: =C7+1 -> 2020 | D8: 261068 | E8: =D8/D7-1 -> -0.13535891
B9: =B8+1 -> 7 | C9: =C8+1 -> 2021 | D9: 249795 | E9: =D9/D8-1 -> -0.043180321
B10: =B9+1 -> 8 | C10: =C9+1 -> 2022 | D10: 278454 | E10: =D10/D9-1 -> 0.11473008 | G10: SUMMARY OUTPUT
B11: =B10+1 -> 9 | C11: =C10+1 -> 2023 | D11: 345967 | E11: =D11/D10-1 -> 0.24245656
B12: =B11+1 -> 10 | C12: =C11+1 -> 2024 | D12: 434016 | E12: =D12/D11-1 -> 0.25450115 | G12: Regression Statistics
B13: =B12+1 -> 11 | C13: =C12+1 -> 2025 | D13: 439695 | E13: =D13/D12-1 -> 0.013084771 | G13: Multiple R | H13: 0.70368468
B14: =B13+1 -> 12 | C14: =C13+1 -> 2026 | D14: 335582 | E14: =D14/D13-1 -> -0.23678459 | G14: R Square | H14: 0.49517212 | I14: Strength of regr should be more than 0.4
B15: =B14+1 -> 13 | C15: =C14+1 -> 2027 | D15: =FORECAST(B15,$D$3:$D$14,$B$3:$B$14) -> 394658.62 | E15: =D15/D14-1 -> 0.17604228 | G15: Adjusted R Square | H15: 0.44468934
B16: =B15+1 -> 14 | C16: =C15+1 -> 2028 | D16: =FORECAST(B16,$D$3:$D$14,$B$3:$B$14) -> 407375.81 | E16: =D16/D15-1 -> 0.032223255 | G16: Standard Error | H16: 48557.083
B17: =B16+1 -> 15 | C17: =C16+1 -> 2029 | D17: =FORECAST(B17,$D$3:$D$14,$B$3:$B$14) -> 420092.99 | E17: =D17/D16-1 -> 0.031217331 | G17: Observations | H17: 12
B18: =B17+1 -> 16 | C18: =C17+1 -> 2030 | D18: =FORECAST(B18,$D$3:$D$14,$B$3:$B$14) -> 432810.18 | E18: =D18/D17-1 -> 0.03027231
B19: =B18+1 -> 17 | C19: =C18+1 -> 2031 | D19: =FORECAST(B19,$D$3:$D$14,$B$3:$B$14) -> 445527.36 | E19: =D19/D18-1 -> 0.029382824 | G19: ANOVA
H20: df | I20: SS | J20: MS | K20: F | L20: Significance F
G21: Regression | H21: 1 | I21: 2.3126933e+10 | J21: 2.3126933e+10 | K21: 9.8087318 | L21: 0.01065618
B22: 13 | C22: 2027 | D22: 394658.62 | E22: 0.17604228 | G22: Residual | H22: 10 | I22: 2.3577903e+10 | J22: 2.3577903e+09
B23: 14 | C23: 2028 | D23: 407375.81 | E23: 0.032223255 | G23: Total | H23: 11 | I23: 4.6704836e+10
B24: 15 | C24: 2029 | D24: 420092.99 | E24: 0.031217331
B25: 16 | C25: 2030 | D25: 432810.18 | E25: 0.03027231 | H25: Coefficients | I25: Standard Error | J25: t Stat | K25: P-value | L25: Lower 95% | M25: Upper 95% | N25: Lower 95.0% | O25: Upper 95.0%
B26: 17 | C26: 2031 | D26: 445527.36 | E26: 0.029382824 | G26: Intercept | H26: 229335.21 | I26: 29884.819 | J26: 7.6739703 | K26: 1.6920326e-05 | L26: 162747.69 | M26: 295922.74 | N26: 162747.69 | O26: 295922.74
G27: Year Weight | H27: 12717.185 | I27: 4060.5473 | J27: 3.1318895 | K27: 0.01065618 | L27: 3669.7222 | M27: 21764.648 | N27: 3669.7222 | O27: 21764.648

Sheet Sheet2
B2: ='Data Sheet'!$B$1&" - "&'Data Sheet'!$A$17&" Forecasting" -> SUN PHARMACEUTICAL INDUSTRIES LTD - Sales Forecasting | G2: ='Data Sheet'!$B$1&" - "&HistoricalFS!B18&" Forecasting" -> SUN PHARMACEUTICAL INDUSTRIES LTD - EBITDA Forecasting | L2: ='Data Sheet'!$B$1&" - "&HistoricalFS!B43&" Forecasting" -> SUN PHARMACEUTICAL INDUSTRIES LTD - EPS Forecasting
B3: Year Weight | C3: Year | D3: Sales | E3: Sales Growth | G3: Year Weight | H3: Year | I3: EBITDA | J3: EBITDA Growth | L3: Year Weight | M3: Year | N3: EPS | O3: EPS Growth
B4: 1 | C4: ='Data Sheet'!$B$16 -> 42825 | D4: {=TRANSPOSE('Data Sheet'!B17:K17)} -> 31578.44 | G4: 1 | H4: ='Data Sheet'!$B$16 -> 42825 | I4: {=TRANSPOSE(HistoricalFS!C18:L18)} -> 10102.02 | L4: 1 | M4: ='Data Sheet'!$B$16 -> 42825 | N4: {=TRANSPOSE(HistoricalFS!C43:L43)} -> 32.660776
B5: =B4+1 -> 2 | C5: =C4+365 -> 43190 | D5: 26489.46 | E5: =D5/D4-1 -> -0.16115362 | G5: =G4+1 -> 2 | H5: =H4+365 -> 43190 | I5: 5631.42 | J5: =I5/I4-1 -> -0.44254515 | L5: =L4+1 -> 2 | M5: =M4+365 -> 43190 | N5: 10.702872 | O5: =N5/N4-1 -> -0.67230198
B6: =B5+1 -> 3 | C6: =C5+365 -> 43555 | D6: 29065.91 | E6: =D6/D5-1 -> 0.097263213 | G6: =G5+1 -> 3 | H6: =H5+365 -> 43555 | I6: 6376.98 | J6: =I6/I5-1 -> 0.1323929 | L6: =L5+1 -> 3 | M6: =M5+365 -> 43555 | N6: 13.376068 | O6: =N6/N5-1 -> 0.2497644
B7: =B6+1 -> 4 | C7: =C6+365 -> 43920 | D7: 32837.5 | E7: =D7/D6-1 -> 0.12975991 | G7: =G6+1 -> 4 | H7: =H6+365 -> 43920 | I7: 6982.84 | J7: =I7/I6-1 -> 0.095007355 | L7: =L6+1 -> 4 | M7: =M6+365 -> 43920 | N7: 17.450048 | O7: =N7/N6-1 -> 0.30457231
B8: =B7+1 -> 5 | C8: =C7+365 -> 44285 | D8: 33498.14 | E8: =D8/D7-1 -> 0.020118462 | G8: =G7+1 -> 5 | H8: =H7+365 -> 44285 | I8: 8469.96 | J8: =I8/I7-1 -> 0.21296779 | L8: =L7+1 -> 5 | M8: =M7+365 -> 44285 | N8: 9.5222773 | O8: =N8/N7-1 -> -0.45431225
B9: =B8+1 -> 6 | C9: =C8+365 -> 44650 | D9: 38654.49 | E9: =D9/D8-1 -> 0.15392944 | G9: =G8+1 -> 6 | H9: =H8+365 -> 44650 | I9: 10257.57 | J9: =I9/I8-1 -> 0.21105294 | L9: =L8+1 -> 6 | M9: =M8+365 -> 44650 | N9: 14.195057 | O9: =N9/N8-1 -> 0.4907208
B10: =B9+1 -> 7 | C10: =C9+365 -> 45015 | D10: 43885.68 | E10: =D10/D9-1 -> 0.13533201 | G10: =G9+1 -> 7 | H10: =H9+365 -> 45015 | I10: 11650.44 | J10: =I10/I9-1 -> 0.13578947 | L10: =L9+1 -> 7 | M10: =M9+365 -> 45015 | N10: 35.680574 | O10: =N10/N9-1 -> 1.5135914
B11: =B10+1 -> 8 | C11: =C10+365 -> 45380 | D11: 48496.85 | E11: =D11/D10-1 -> 0.10507232 | G11: =G10+1 -> 8 | H11: =H10+365 -> 45380 | I11: 13017.77 | J11: =I11/I10-1 -> 0.11736295 | L11: =L10+1 -> 8 | M11: =M10+365 -> 45380 | N11: 40.213562 | O11: =N11/N10-1 -> 0.12704361
B12: =B11+1 -> 9 | C12: =C11+365 -> 45745 | D12: 52578.44 | E12: =D12/D11-1 -> 0.084161961 | G12: =G11+1 -> 9 | H12: =H11+365 -> 45745 | I12: 15114.46 | J12: =I12/I11-1 -> 0.16106368 | L12: =L11+1 -> 9 | M12: =M11+365 -> 45745 | N12: 45.763764 | O12: =N12/N11-1 -> 0.13801817
B13: =B12+1 -> 10 | C13: =C12+365 -> 46110 | D13: 58462.04 | E13: =D13/D12-1 -> 0.11190138 | G13: =G12+1 -> 10 | H13: =H12+365 -> 46110 | I13: 17731.4 | J13: =I13/I12-1 -> 0.17314148 | L13: =L12+1 -> 10 | M13: =M12+365 -> 46110 | N13: 48.199558 | O13: =N13/N12-1 -> 0.05322538
B14: =B13+1 -> 11 | C14: =C13+365 -> 46475 | D14: =FORECAST(B14,$D$4:$D$13,$B$4:$B$13) -> 58222.39 | E14: =D14/D13-1 -> -0.0040992411 | G14: =G13+1 -> 11 | H14: =H13+365 -> 46475 | I14: =FORECAST(G14,$I$4:$I$13,$G$4:$G$13) -> 16668.155 | J14: =I14/I13-1 -> -0.059963981 | L14: =L13+1 -> 11 | M14: =M13+365 -> 46475 | N14: =FORECAST(L14,$N$4:$N$13,$L$4:$L$13) -> 46.070693 | O14: =N14/N13-1 -> -0.044167736
B15: =B14+1 -> 12 | C15: =C14+365 -> 46840 | D15: =FORECAST(B15,$D$4:$D$13,$B$4:$B$13) -> 61616.516 | E15: =D15/D14-1 -> 0.058295896 | G15: =G14+1 -> 12 | H15: =H14+365 -> 46840 | I15: =FORECAST(G15,$I$4:$I$13,$G$4:$G$13) -> 17783.549 | J15: =I15/I14-1 -> 0.066917684 | L15: =L14+1 -> 12 | M15: =M14+365 -> 46840 | N15: =FORECAST(L15,$N$4:$N$13,$L$4:$L$13) -> 49.578736 | O15: =N15/N14-1 -> 0.076144788
B16: =B15+1 -> 13 | C16: =C15+365 -> 47205 | D16: =FORECAST(B16,$D$4:$D$13,$B$4:$B$13) -> 65010.643 | E16: =D16/D15-1 -> 0.055084684 | G16: =G15+1 -> 13 | H16: =H15+365 -> 47205 | I16: =FORECAST(G16,$I$4:$I$13,$G$4:$G$13) -> 18898.943 | J16: =I16/I15-1 -> 0.062720569 | L16: =L15+1 -> 13 | M16: =M15+365 -> 47205 | N16: =FORECAST(L16,$N$4:$N$13,$L$4:$L$13) -> 53.086779 | O16: =N16/N15-1 -> 0.07075701
B17: =B16+1 -> 14 | C17: =C16+365 -> 47570 | D17: =FORECAST(B17,$D$4:$D$13,$B$4:$B$13) -> 68404.769 | E17: =D17/D16-1 -> 0.05220878 | G17: =G16+1 -> 14 | H17: =H16+365 -> 47570 | I17: =FORECAST(G17,$I$4:$I$13,$G$4:$G$13) -> 20014.338 | J17: =I17/I16-1 -> 0.059018871 | L17: =L16+1 -> 14 | M17: =M16+365 -> 47570 | N17: =FORECAST(L17,$N$4:$N$13,$L$4:$L$13) -> 56.594822 | O17: =N17/N16-1 -> 0.066081295
B18: =B17+1 -> 15 | C18: =C17+365 -> 47935 | D18: =FORECAST(B18,$D$4:$D$13,$B$4:$B$13) -> 71798.895 | E18: =D18/D17-1 -> 0.049618271 | G18: =G17+1 -> 15 | H18: =H17+365 -> 47935 | I18: =FORECAST(G18,$I$4:$I$13,$G$4:$G$13) -> 21129.732 | J18: =I18/I17-1 -> 0.055729764 | L18: =L17+1 -> 15 | M18: =M17+365 -> 47935 | N18: =FORECAST(L18,$N$4:$N$13,$L$4:$L$13) -> 60.102865 | O18: =N18/N17-1 -> 0.061985231

Sheet Common Size Statement
A2: # | B2: ="Commom Size Income Statement"&" "&"- "&'[1]Data Set'!$B$1 -> Commom Size Income Statement - SUN PHARMACEUTICAL INDUSTRIES LTD | C2: ="Commom Size Income Statement"&" "&"- "&'[1]Data Set'!$B$1 -> Commom Size Income Statement - SUN PHARMACEUTICAL INDUSTRIES LTD | D2: ="Commom Size Income Statement"&" "&"- "&'[1]Data Set'!$B$1 -> Commom Size Income Statement - SUN PHARMACEUTICAL INDUSTRIES LTD | E2: ="Commom Size Income Statement"&" "&"- "&'[1]Data Set'!$B$1 -> Commom Size Income Statement - SUN PHARMACEUTICAL INDUSTRIES LTD | F2: ="Commom Size Income Statement"&" "&"- "&'[1]Data Set'!$B$1 -> Commom Size Income Statement - SUN PHARMACEUTICAL INDUSTRIES LTD | G2: ="Commom Size Income Statement"&" "&"- "&'[1]Data Set'!$B$1 -> Commom Size Income Statement - SUN PHARMACEUTICAL INDUSTRIES LTD | H2: ="Commom Size Income Statement"&" "&"- "&'[1]Data Set'!$B$1 -> Commom Size Income Statement - SUN PHARMACEUTICAL INDUSTRIES LTD | I2: ="Commom Size Income Statement"&" "&"- "&'[1]Data Set'!$B$1 -> Commom Size Income Statement - SUN PHARMACEUTICAL INDUSTRIES LTD | ... L2: ="Commom Size Income Statement"&" "&"- "&'[1]Data Set'!$B$1 -> Commom Size Income Statement - SUN PHARMACEUTICAL INDUSTRIES LTD
B4: Particulars | C4: ='Data Sheet'!B16 -> 42825 | D4: ='Data Sheet'!C16 -> 43190 | E4: ='Data Sheet'!D16 -> 43555 | F4: ='Data Sheet'!E16 -> 43921 | G4: ='Data Sheet'!F16 -> 44286 | H4: ='Data Sheet'!G16 -> 44651 | I4: ='Data Sheet'!H16 -> 45016 | J4: ='Data Sheet'!I16 -> 45382 | ... L4: ='Data Sheet'!K16 -> 46112
B6: ='Data Sheet'!A17 -> Sales | C6: ='Data Sheet'!B17/'Data Sheet'!B$17 -> 1 | D6: ='Data Sheet'!C17/'Data Sheet'!C$17 -> 1 | E6: ='Data Sheet'!D17/'Data Sheet'!D$17 -> 1 | F6: ='Data Sheet'!E17/'Data Sheet'!E$17 -> 1 | G6: ='Data Sheet'!F17/'Data Sheet'!F$17 -> 1 | H6: ='Data Sheet'!G17/'Data Sheet'!G$17 -> 1 | I6: ='Data Sheet'!H17/'Data Sheet'!H$17 -> 1 | J6: ='Data Sheet'!I17/'Data Sheet'!I$17 -> 1 | ... L6: ='Data Sheet'!K17/'Data Sheet'!K$17 -> 1
B7: ='Data Sheet'!A18 -> Raw Material Cost | C7: ='Data Sheet'!B18/'Data Sheet'!B$17 -> 0.26607933 | D7: ='Data Sheet'!C18/'Data Sheet'!C$17 -> 0.27157896 | E7: ='Data Sheet'!D18/'Data Sheet'!D$17 -> 0.28562945 | F7: ='Data Sheet'!E18/'Data Sheet'!E$17 -> 0.271933 | G7: ='Data Sheet'!F18/'Data Sheet'!F$17 -> 0.27847218 | H7: ='Data Sheet'!G18/'Data Sheet'!G$17 -> 0.27058047 | I7: ='Data Sheet'!H18/'Data Sheet'!H$17 -> 0.25860531 | J7: ='Data Sheet'!I18/'Data Sheet'!I$17 -> 0.21383822 | ... L7: ='Data Sheet'!K18/'Data Sheet'!K$17 -> 0.19158671
B8: ='Data Sheet'!A19 -> Change in Inventory | C8: ='Data Sheet'!B19/'Data Sheet'!B$17 -> 0.0086017549 | D8: ='Data Sheet'!C19/'Data Sheet'!C$17 -> -0.0087091243 | E8: ='Data Sheet'!D19/'Data Sheet'!D$17 -> 0.014900961 | F8: ='Data Sheet'!E19/'Data Sheet'!E$17 -> -0.0091617815 | G8: ='Data Sheet'!F19/'Data Sheet'!F$17 -> 0.019052401 | H8: ='Data Sheet'!G19/'Data Sheet'!G$17 -> 0.0027838939 | I8: ='Data Sheet'!H19/'Data Sheet'!H$17 -> 0.015652258 | J8: ='Data Sheet'!I19/'Data Sheet'!I$17 -> -0.0060236902 | ... L8: ='Data Sheet'!K19/'Data Sheet'!K$17 -> -0.0058692786
B9: ='Data Sheet'!A20 -> Power and Fuel | C9: ='Data Sheet'!B20/'Data Sheet'!B$17 -> 0.016628117 | D9: ='Data Sheet'!C20/'Data Sheet'!C$17 -> 0.021139351 | E9: ='Data Sheet'!D20/'Data Sheet'!D$17 -> 0.021110641 | F9: ='Data Sheet'!E20/'Data Sheet'!E$17 -> 0.018938409 | G9: ='Data Sheet'!F20/'Data Sheet'!F$17 -> 0.018720144 | H9: ='Data Sheet'!G20/'Data Sheet'!G$17 -> 0.01818107 | I9: ='Data Sheet'!H20/'Data Sheet'!H$17 -> 0.018913915 | J9: ='Data Sheet'!I20/'Data Sheet'!I$17 -> 0.015687204 | ... L9: ='Data Sheet'!K20/'Data Sheet'!K$17 -> 0
B10: ='Data Sheet'!A21 -> Other Mfr. Exp | C10: ='Data Sheet'!B21/'Data Sheet'!B$17 -> 0.062493904 | D10: ='Data Sheet'!C21/'Data Sheet'!C$17 -> 0.069021792 | E10: ='Data Sheet'!D21/'Data Sheet'!D$17 -> 0.064842628 | F10: ='Data Sheet'!E21/'Data Sheet'!E$17 -> 0.05146555 | G10: ='Data Sheet'!F21/'Data Sheet'!F$17 -> 0.051458977 | H10: ='Data Sheet'!G21/'Data Sheet'!G$17 -> 0.048654374 | I10: ='Data Sheet'!H21/'Data Sheet'!H$17 -> 0.044132163 | J10: ='Data Sheet'!I21/'Data Sheet'!I$17 -> 0.045087877 | ... L10: ='Data Sheet'!K21/'Data Sheet'!K$17 -> 0
B11: ='Data Sheet'!A22 -> Employee Cost | C11: ='Data Sheet'!B22/'Data Sheet'!B$17 -> 0.15524199 | D11: ='Data Sheet'!C22/'Data Sheet'!C$17 -> 0.20261077 | E11: ='Data Sheet'!D22/'Data Sheet'!D$17 -> 0.20529514 | F11: ='Data Sheet'!E22/'Data Sheet'!E$17 -> 0.19375257 | G11: ='Data Sheet'!F22/'Data Sheet'!F$17 -> 0.20485406 | H11: ='Data Sheet'!G22/'Data Sheet'!G$17 -> 0.18887405 | I11: ='Data Sheet'!H22/'Data Sheet'!H$17 -> 0.18903729 | J11: ='Data Sheet'!I22/'Data Sheet'!I$17 -> 0.19442624 | ... L11: ='Data Sheet'!K22/'Data Sheet'!K$17 -> 0.19532093
B12: ='Data Sheet'!A23 -> Selling and admin | C12: ='Data Sheet'!B23/'Data Sheet'!B$17 -> 0.16544864 | D12: ='Data Sheet'!C23/'Data Sheet'!C$17 -> 0.17844833 | E12: ='Data Sheet'!D23/'Data Sheet'!D$17 -> 0.18407578 | F12: ='Data Sheet'!E23/'Data Sheet'!E$17 -> 0.21302992 | G12: ='Data Sheet'!F23/'Data Sheet'!F$17 -> 0.18757489 | H12: ='Data Sheet'!G23/'Data Sheet'!G$17 -> 0.19058278 | I12: ='Data Sheet'!H23/'Data Sheet'!H$17 -> 0.21606957 | J12: ='Data Sheet'!I23/'Data Sheet'!I$17 -> 0.22750323 | ... L12: ='Data Sheet'!K23/'Data Sheet'!K$17 -> 0
B13: ='Data Sheet'!A24 -> Other Expenses | C13: ='Data Sheet'!B24/'Data Sheet'!B$17 -> 0.022807333 | D13: ='Data Sheet'!C24/'Data Sheet'!C$17 -> 0.035900694 | E13: ='Data Sheet'!D24/'Data Sheet'!D$17 -> 0.034550097 | F13: ='Data Sheet'!E24/'Data Sheet'!E$17 -> 0.029070423 | G13: ='Data Sheet'!F24/'Data Sheet'!F$17 -> 0.025123484 | H13: ='Data Sheet'!G24/'Data Sheet'!G$17 -> 0.020545608 | I13: ='Data Sheet'!H24/'Data Sheet'!H$17 -> 0.023421535 | J13: ='Data Sheet'!I24/'Data Sheet'!I$17 -> 0.029008482 | ... L13: ='Data Sheet'!K24/'Data Sheet'!K$17 -> 0.30392542
B14: ='Data Sheet'!A25 -> Other Income | C14: ='Data Sheet'!B25/'Data Sheet'!B$17 -> 0.019329644 | D14: ='Data Sheet'!C25/'Data Sheet'!C$17 -> -0.0050974992 | E14: ='Data Sheet'!D25/'Data Sheet'!D$17 -> -0.0088860111 | F14: ='Data Sheet'!E25/'Data Sheet'!E$17 -> 0.011640959 | G14: ='Data Sheet'!F25/'Data Sheet'!F$17 -> -0.10296721 | H14: ='Data Sheet'!G25/'Data Sheet'!G$17 -> -0.090679246 | I14: ='Data Sheet'!H25/'Data Sheet'!H$17 -> 0.010468563 | J14: ='Data Sheet'!I25/'Data Sheet'!I$17 -> 0.017840953 | ... L14: ='Data Sheet'!K25/'Data Sheet'!K$17 -> 0.011361903
B15: ='Data Sheet'!A26 -> Depreciation | C15: ='Data Sheet'!B26/'Data Sheet'!B$17 -> 0.04005106 | D15: ='Data Sheet'!C26/'Data Sheet'!C$17 -> 0.056620256 | E15: ='Data Sheet'!D26/'Data Sheet'!D$17 -> 0.060319804 | F15: ='Data Sheet'!E26/'Data Sheet'!E$17 -> 0.062513285 | G15: ='Data Sheet'!F26/'Data Sheet'!F$17 -> 0.062091507 | H15: ='Data Sheet'!G26/'Data Sheet'!G$17 -> 0.055459017 | I15: ='Data Sheet'!H26/'Data Sheet'!H$17 -> 0.057636796 | J15: ='Data Sheet'!I26/'Data Sheet'!I$17 -> 0.052717651 | ... L15: ='Data Sheet'!K26/'Data Sheet'!K$17 -> 0.050252266
B16: ='Data Sheet'!A27 -> Interest | C16: ='Data Sheet'!B27/'Data Sheet'!B$17 -> 0.012660537 | D16: ='Data Sheet'!C27/'Data Sheet'!C$17 -> 0.019538715 | E16: ='Data Sheet'!D27/'Data Sheet'!D$17 -> 0.019103135 | F16: ='Data Sheet'!E27/'Data Sheet'!E$17 -> 0.0092190331 | G16: ='Data Sheet'!F27/'Data Sheet'!F$17 -> 0.0042220255 | H16: ='Data Sheet'!G27/'Data Sheet'!G$17 -> 0.003294572 | I16: ='Data Sheet'!H27/'Data Sheet'!H$17 -> 0.0039192739 | J16: ='Data Sheet'!I27/'Data Sheet'!I$17 -> 0.0049172266 | ... L16: ='Data Sheet'!K27/'Data Sheet'!K$17 -> 0.005797095
B17: ='Data Sheet'!A28 -> Profit before tax | C17: ='Data Sheet'!B28/'Data Sheet'!B$17 -> 0.28652049 | D17: ='Data Sheet'!C28/'Data Sheet'!C$17 -> 0.1313345 | E17: ='Data Sheet'!D28/'Data Sheet'!D$17 -> 0.13108827 | F17: ='Data Sheet'!E28/'Data Sheet'!E$17 -> 0.15255699 | G17: ='Data Sheet'!F28/'Data Sheet'!F$17 -> 0.083567923 | H17: ='Data Sheet'!G28/'Data Sheet'!G$17 -> 0.11593272 | I17: ='Data Sheet'!H28/'Data Sheet'!H$17 -> 0.21438497 | J17: ='Data Sheet'!I28/'Data Sheet'!I$17 -> 0.22863114 | ... L17: ='Data Sheet'!K28/'Data Sheet'!K$17 -> 0.2586102
... B21: ='Data Sheet'!A32 -> EBITDA | C21: ='Data Sheet'!B32/'Data Sheet'!B$17 -> 0.31162052 | D21: ='Data Sheet'!C32/'Data Sheet'!C$17 -> 0.189666 | E21: ='Data Sheet'!D32/'Data Sheet'!D$17 -> 0.19179857 | F21: ='Data Sheet'!E32/'Data Sheet'!E$17 -> 0.21144241 | G21: ='Data Sheet'!F32/'Data Sheet'!F$17 -> 0.16836427 | H21: ='Data Sheet'!G32/'Data Sheet'!G$17 -> 0.17124324 | I21: ='Data Sheet'!H32/'Data Sheet'!H$17 -> 0.27395269 | J21: ='Data Sheet'!I32/'Data Sheet'!I$17 -> 0.28478015 | ... L21: ='Data Sheet'!K32/'Data Sheet'!K$17 -> 0.31320392
A24: # | B24: ="Commom Size Balance Sheet"&" "&"- "&'[1]Data Set'!$B$1 -> Commom Size Balance Sheet - SUN PHARMACEUTICAL INDUSTRIES LTD | C24: ="Commom Size Income Statement"&" "&"- "&'[1]Data Set'!$B$1 -> Commom Size Income Statement - SUN PHARMACEUTICAL INDUSTRIES LTD | D24: ="Commom Size Income Statement"&" "&"- "&'[1]Data Set'!$B$1 -> Commom Size Income Statement - SUN PHARMACEUTICAL INDUSTRIES LTD | E24: ="Commom Size Income Statement"&" "&"- "&'[1]Data Set'!$B$1 -> Commom Size Income Statement - SUN PHARMACEUTICAL INDUSTRIES LTD | F24: ="Commom Size Income Statement"&" "&"- "&'[1]Data Set'!$B$1 -> Commom Size Income Statement - SUN PHARMACEUTICAL INDUSTRIES LTD | G24: ="Commom Size Income Statement"&" "&"- "&'[1]Data Set'!$B$1 -> Commom Size Income Statement - SUN PHARMACEUTICAL INDUSTRIES LTD | H24: ="Commom Size Income Statement"&" "&"- "&'[1]Data Set'!$B$1 -> Commom Size Income Statement - SUN PHARMACEUTICAL INDUSTRIES LTD | I24: ="Commom Size Income Statement"&" "&"- "&'[1]Data Set'!$B$1 -> Commom Size Income Statement - SUN PHARMACEUTICAL INDUSTRIES LTD | J24: ="Commom Size Income Statement"&" "&"- "&'[1]Data Set'!$B$1 -> Commom Size Income Statement - SUN PHARMACEUTICAL INDUSTRIES LTD | ... L24: ="Commom Size Income Statement"&" "&"- "&'[1]Data Set'!$B$1 -> Commom Size Income Statement - SUN PHARMACEUTICAL INDUSTRIES LTD
B26: Particulars | C26: ='Data Sheet'!B56 -> 42825 | D26: ='Data Sheet'!C56 -> 43190 | E26: ='Data Sheet'!D56 -> 43555 | F26: ='Data Sheet'!E56 -> 43921 | G26: ='Data Sheet'!F56 -> 44286 | H26: ='Data Sheet'!G56 -> 44651 | I26: ='Data Sheet'!H56 -> 45016 | J26: ='Data Sheet'!I56 -> 45382 | ... L26: ='Data Sheet'!K56 -> 46112
B28: Total Liabilities | C28: ='Data Sheet'!B61/'Data Sheet'!B$61 -> 1 | D28: ='Data Sheet'!C61/'Data Sheet'!C$61 -> 1 | E28: ='Data Sheet'!D61/'Data Sheet'!D$61 -> 1 | F28: ='Data Sheet'!E61/'Data Sheet'!E$61 -> 1 | G28: ='Data Sheet'!F61/'Data Sheet'!F$61 -> 1 | H28: ='Data Sheet'!G61/'Data Sheet'!G$61 -> 1 | I28: ='Data Sheet'!H61/'Data Sheet'!H$61 -> 1 | J28: ='Data Sheet'!I61/'Data Sheet'!I$61 -> 1 | ... L28: ='Data Sheet'!K61/'Data Sheet'!K$61 -> 1
B29: ='Data Sheet'!A57 -> Equity Share Capital | C29: ='Data Sheet'!B57/'Data Sheet'!B$61 -> 0.0039271337 | D29: ='Data Sheet'!C57/'Data Sheet'!C$61 -> 0.0037315667 | E29: ='Data Sheet'!D57/'Data Sheet'!D$61 -> 0.0037146887 | F29: ='Data Sheet'!E57/'Data Sheet'!E$61 -> 0.0035183282 | G29: ='Data Sheet'!F57/'Data Sheet'!F$61 -> 0.0035480941 | H29: ='Data Sheet'!G57/'Data Sheet'!G$61 -> 0.0034385793 | I29: ='Data Sheet'!H57/'Data Sheet'!H$61 -> 0.0029726719 | J29: ='Data Sheet'!I57/'Data Sheet'!I$61 -> 0.0028118623 | ... L29: ='Data Sheet'!K57/'Data Sheet'!K$61 -> 0.0022055386
B30: ='Data Sheet'!A58 -> Reserves | C30: ='Data Sheet'!B58/'Data Sheet'!B$61 -> 0.59578479 | D30: ='Data Sheet'!C58/'Data Sheet'!C$61 -> 0.59215747 | E30: ='Data Sheet'!D58/'Data Sheet'!D$61 -> 0.63739634 | F30: ='Data Sheet'!E58/'Data Sheet'!E$61 -> 0.66023857 | G30: ='Data Sheet'!F58/'Data Sheet'!F$61 -> 0.68354529 | H30: ='Data Sheet'!G58/'Data Sheet'!G$61 -> 0.68463872 | I30: ='Data Sheet'!H58/'Data Sheet'!H$61 -> 0.6907959 | J30: ='Data Sheet'!I58/'Data Sheet'!I$61 -> 0.74333133 | ... L30: ='Data Sheet'!K58/'Data Sheet'!K$61 -> 0.76600626
B31: ='Data Sheet'!A59 -> Borrowings | C31: ='Data Sheet'!B59/'Data Sheet'!B$61 -> 0.16092475 | D31: ='Data Sheet'!C59/'Data Sheet'!C$61 -> 0.16151931 | E31: ='Data Sheet'!D59/'Data Sheet'!D$61 -> 0.16278737 | F31: ='Data Sheet'!E59/'Data Sheet'!E$61 -> 0.12192922 | G31: ='Data Sheet'!F59/'Data Sheet'!F$61 -> 0.05720871 | H31: ='Data Sheet'!G59/'Data Sheet'!G$61 -> 0.018492055 | I31: ='Data Sheet'!H59/'Data Sheet'!H$61 -> 0.085314185 | J31: ='Data Sheet'!I59/'Data Sheet'!I$61 -> 0.038365813 | ... L31: ='Data Sheet'!K59/'Data Sheet'!K$61 -> 0.042536293
B32: ='Data Sheet'!A60 -> Other Liabilities | C32: ='Data Sheet'!B60/'Data Sheet'!B$61 -> 0.23936332 | D32: ='Data Sheet'!C60/'Data Sheet'!C$61 -> 0.24259165 | E32: ='Data Sheet'!D60/'Data Sheet'!D$61 -> 0.1961016 | F32: ='Data Sheet'!E60/'Data Sheet'!E$61 -> 0.21431389 | G32: ='Data Sheet'!F60/'Data Sheet'!F$61 -> 0.25569791 | H32: ='Data Sheet'!G60/'Data Sheet'!G$61 -> 0.29343064 | I32: ='Data Sheet'!H60/'Data Sheet'!H$61 -> 0.22091724 | J32: ='Data Sheet'!I60/'Data Sheet'!I$61 -> 0.21549099 | ... L32: ='Data Sheet'!K60/'Data Sheet'!K$61 -> 0.1892519
B34: Total Assets | C34: ='Data Sheet'!B75/'Data Sheet'!B$75 -> 1 | D34: ='Data Sheet'!C75/'Data Sheet'!C$75 -> 1 | E34: ='Data Sheet'!D75/'Data Sheet'!D$75 -> 1 | F34: ='Data Sheet'!E75/'Data Sheet'!E$75 -> 1 | G34: ='Data Sheet'!F75/'Data Sheet'!F$75 -> 1 | H34: ='Data Sheet'!G75/'Data Sheet'!G$75 -> 1 | I34: ='Data Sheet'!H75/'Data Sheet'!H$75 -> 1 | J34: ='Data Sheet'!I75/'Data Sheet'!I$75 -> 1 | ... L34: ='Data Sheet'!K75/'Data Sheet'!K$75 -> 1
B35: ='Data Sheet'!A62 -> Net Block | C35: ='Data Sheet'!B62/'Data Sheet'!B$75 -> 0.2893042 | D35: ='Data Sheet'!C62/'Data Sheet'!C$75 -> 0.29321019 | E35: ='Data Sheet'!D62/'Data Sheet'!D$75 -> 0.33808173 | F35: ='Data Sheet'!E62/'Data Sheet'!E$75 -> 0.33502658 | G35: ='Data Sheet'!F62/'Data Sheet'!F$75 -> 0.3187263 | H35: ='Data Sheet'!G62/'Data Sheet'!G$75 -> 0.32482787 | I35: ='Data Sheet'!H62/'Data Sheet'!H$75 -> 0.29816471 | J35: ='Data Sheet'!I62/'Data Sheet'!I$75 -> 0.27245696 | ... L35: ='Data Sheet'!K62/'Data Sheet'!K$75 -> 0.31707754
B36: ='Data Sheet'!A63 -> Capital Work in Progress | C36: ='Data Sheet'!B63/'Data Sheet'!B$75 -> 0.045852514 | D36: ='Data Sheet'!C63/'Data Sheet'!C$75 -> 0.03833997 | E36: ='Data Sheet'!D63/'Data Sheet'!D$75 -> 0.021847968 | F36: ='Data Sheet'!E63/'Data Sheet'!E$75 -> 0.017895039 | G36: ='Data Sheet'!F63/'Data Sheet'!F$75 -> 0.023170343 | H36: ='Data Sheet'!G63/'Data Sheet'!G$75 -> 0.018441895 | I36: ='Data Sheet'!H63/'Data Sheet'!H$75 -> 0.061616193 | J36: ='Data Sheet'!I63/'Data Sheet'!I$75 -> 0.062744857 | ... L36: ='Data Sheet'!K63/'Data Sheet'!K$75 -> 0.012691522
B37: ='Data Sheet'!A64 -> Investments | C37: ='Data Sheet'!B64/'Data Sheet'!B$75 -> 0.01950849 | D37: ='Data Sheet'!C64/'Data Sheet'!C$75 -> 0.11109113 | E37: ='Data Sheet'!D64/'Data Sheet'!D$75 -> 0.12235002 | F37: ='Data Sheet'!E64/'Data Sheet'!E$75 -> 0.14873834 | G37: ='Data Sheet'!F64/'Data Sheet'!F$75 -> 0.14214928 | H37: ='Data Sheet'!G64/'Data Sheet'!G$75 -> 0.18414077 | I37: ='Data Sheet'!H64/'Data Sheet'!H$75 -> 0.18366982 | J37: ='Data Sheet'!I64/'Data Sheet'!I$75 -> 0.17609468 | ... L37: ='Data Sheet'!K64/'Data Sheet'!K$75 -> 0.22725992
B38: ='Data Sheet'!A65 -> Other Assets | C38: ='Data Sheet'!B74/'Data Sheet'!B$75 -> 0.16778271 | D38: ='Data Sheet'!C74/'Data Sheet'!C$75 -> 0.17436726 | E38: ='Data Sheet'!D74/'Data Sheet'!D$75 -> 0.14543425 | F38: ='Data Sheet'!E74/'Data Sheet'!E$75 -> 0.14957521 | G38: ='Data Sheet'!F74/'Data Sheet'!F$75 -> 0.15358901 | H38: ='Data Sheet'!G74/'Data Sheet'!G$75 -> 0.12228131 | I38: ='Data Sheet'!H74/'Data Sheet'!H$75 -> 0.11308258 | J38: ='Data Sheet'!I74/'Data Sheet'!I$75 -> 0.11791762 | ... L38: ='Data Sheet'!K74/'Data Sheet'!K$75 -> 0.088091195
B39: ='Data Sheet'!A67 -> Receivables | C39: ='Data Sheet'!B67/'Data Sheet'!B$75 -> 0.1178911 | D39: ='Data Sheet'!C67/'Data Sheet'!C$75 -> 0.12154895 | E39: ='Data Sheet'!D67/'Data Sheet'!D$75 -> 0.13754861 | F39: ='Data Sheet'!E67/'Data Sheet'!E$75 -> 0.13815285 | G39: ='Data Sheet'!F67/'Data Sheet'!F$75 -> 0.13400033 | H39: ='Data Sheet'!G67/'Data Sheet'!G$75 -> 0.15026089 | I39: ='Data Sheet'!H67/'Data Sheet'!H$75 -> 0.14172024 | J39: ='Data Sheet'!I67/'Data Sheet'!I$75 -> 0.13183712 | ... L39: ='Data Sheet'!K67/'Data Sheet'!K$75 -> 0.14257148
B40: ='Data Sheet'!A68 -> Inventory | C40: ='Data Sheet'!B68/'Data Sheet'!B$75 -> 0.11183828 | D40: ='Data Sheet'!C68/'Data Sheet'!C$75 -> 0.10701352 | E40: ='Data Sheet'!D68/'Data Sheet'!D$75 -> 0.12209378 | F40: ='Data Sheet'!E68/'Data Sheet'!E$75 -> 0.11547868 | G40: ='Data Sheet'!F68/'Data Sheet'!F$75 -> 0.13304828 | H40: ='Data Sheet'!G68/'Data Sheet'!G$75 -> 0.12791134 | I40: ='Data Sheet'!H68/'Data Sheet'!H$75 -> 0.13025403 | J40: ='Data Sheet'!I68/'Data Sheet'!I$75 -> 0.11565154 | ... L40: ='Data Sheet'!K68/'Data Sheet'!K$75 -> 0.1056479
B41: ='Data Sheet'!A69 -> Cash & Bank | C41: ='Data Sheet'!B69/'Data Sheet'!B$75 -> 0.24782271 | D41: ='Data Sheet'!C69/'Data Sheet'!C$75 -> 0.15442897 | E41: ='Data Sheet'!D69/'Data Sheet'!D$75 -> 0.11264364 | F41: ='Data Sheet'!E69/'Data Sheet'!E$75 -> 0.09513329 | G41: ='Data Sheet'!F69/'Data Sheet'!F$75 -> 0.095316451 | H41: ='Data Sheet'!G69/'Data Sheet'!G$75 -> 0.072135928 | I41: ='Data Sheet'!H69/'Data Sheet'!H$75 -> 0.071492432 | J41: ='Data Sheet'!I69/'Data Sheet'!I$75 -> 0.12329723 | ... L41: ='Data Sheet'!K69/'Data Sheet'!K$75 -> 0.10666045

Sheet WACC
B6: Weighted Average Cost of Capital
B8: all Figures are in INR unless stated otherwise
B10: Peer Comps
H11: Debt / | I11: Debt / | J11: Levered | K11: Unlevered
B12: Name of the Comp | D12: Country | E12: Total Debt | F12: Total Equity | G12: Tax Rate 1 | H12: Equity | I12: Capital | J12: Beta 2 | K12: Beta 3
B14: Hind. Unilever | D14: India | E14: 1139 | F14: 611503.89 | G14: 0.3 | H14: =E14/F14 -> 0.001862621 | I14: =E14/(E14+F14) -> 0.0018591581 | J14: 1 | K14: =J14/(1+(1-G14)*H14) -> 0.99869786
B15: Nestle India | D15: India | E15: 279.9 | F15: 182975.03 | G15: 0.3 | H15: =E15/F15 -> 0.0015297169 | I15: =E15/(E15+F15) -> 0.0015273805 | J15: 1 | K15: =J15/(1+(1-G15)*H15) -> 0.99893034
B16: Britannia Inds | D16: India | E16: 3037.7 | F16: 110689.96 | G16: 0.3 | H16: =E16/F16 -> 0.02744332 | I16: =E16/(E16+F16) -> 0.026710301 | J16: 1 | K16: =J16/(1+(1-G16)*H16) -> 0.98115176
B17: Godrej Consumer | D17: India | E17: 1164.5 | F17: 96256.38 | G17: 0.3 | H17: =E17/F17 -> 0.012097899 | I17: =E17/(E17+F17) -> 0.01195329 | J17: 1 | K17: =J17/(1+(1-G17)*H17) -> 0.99160258
B18: Dabur India | D18: India | E18: 1068.1 | F18: 94940.38 | G18: 0.3 | H18: =E18/F18 -> 0.011250218 | I18: =E18/(E18+F18) -> 0.011125059 | J18: 1 | K18: =J18/(1+(1-G18)*H18) -> 0.99218638
F20: Average | G20: =AVERAGE(G14:G18) -> 0.3 | H20: =AVERAGE(H14:H18) -> 0.010836755 | I20: =AVERAGE(I14:I18) -> 0.010635038 | J20: =AVERAGE(J14:J18) -> 1 | K20: =AVERAGE(K14:K18) -> 0.99251379
F21: Median | G21: =MEDIAN(G14:G18) -> 0.3 | H21: =MEDIAN(H14:H18) -> 0.011250218 | I21: =MEDIAN(I14:I18) -> 0.011125059 | J21: =MEDIAN(J14:J18) -> 1 | K21: =MEDIAN(K14:K18) -> 0.99218638
B24: Cost of Debt | G24: Cost of Equity
B26: Pre-Tax Cost of Debt | E26: 0.084 | G26: Risk Free Rate | K26: 0.065
B27: tax Rate | D27: ` | E27: 0.3 | G27: Equity Risk Premium | K27: 0.08
B28: Post Tax Cost of Debt | E28: =E26*(1-E27) -> 0.0588 | G28: Levered Beta 4 | K28: =K37 -> 1.505535
G29: Cost of Equity | K29: =K26+K27*K28 -> 0.1854428
B32: Capital Structure | G32: Levered Beta
D34: Current | E34: Target | G34: Comps Median Unlevered Beta | K34: =K21 -> 0.99218638
B35: Total Debt | C35: 17440 | D35: =C35/$C$37 -> 0.35087013 | E35: 0.425 | G35: Target Debt / Equity | K35: =E39 -> 0.73913043
B36: Market Capitalization | C36: 32265 | D36: =C36/$C$37 -> 0.64912987 | E36: =E37-E35 -> 0.575 | G36: Tax Rate | K36: =E27 -> 0.3
B37: Total Capital | C37: =SUM(C35:C36) -> 49705 | D37: =C37/$C$37 -> 1 | E37: =D37 -> 1 | G37: Levered Beta | K37: =K34*(1+(1-K36)*K35) -> 1.505535
B39: Debt / Equity | D39: =D35/D36 -> 0.54052379 | E39: =E35/E36 -> 0.73913043 | G39: Weighted Average Cost of Capital
B41: Notes: | J41: Total Cost | K41: Total Weight
B42: 1. Tax Rate Considered as Marginal Tax Rate for the Country | G42: Debt | J42: =E28 -> 0.0588 | K42: =E35 -> 0.425
B43: 2. Levered Beta is based on 5 year Monthly data | G43: Equity | J43: =K29 -> 0.1854428 | K43: =E36 -> 0.575
B44: 3. Unlevered Beta = Levered Beta/(1+(1-Tax Rate)*Debt/Equity) | G44: Weighted Average Cost of Capital | K44: =SUMPRODUCT(J42:J43,K42:K43) -> 0.13161961
B45: 4. Levered Beta = Unlevered Beta*(1+(1-Tax Rate)*Debt/Equity)

Sheet Beta
B2: Regression Beta - 2 Years Weekly
B4: Avenue Supermart Weekly Returns | F4: NIFTY Returns | I4: Beta Drifting
B6: Date | C6: Closing Price | D6: Return | F6: Closing Price | G6: Return | I6: Levered Raw Beta | J6: =N8 -> 1.2421196
B7: 44249 | C7: 2994.2 | F7: 14529.15 | I7: Raw Beta Weight | J7: 0.75 | M7: Beta 1 | N7: =SLOPE(D8:D111,G8:G111) -> 1.2421196
B8: 44256 | C8: 3286.1001 | D8: =C8/C7-1 -> 0.097488528 | F8: 14938.1 | G8: =F8/F7-1 -> 0.028146809 | M8: Beta 2 | N8: =_xlfn.COVARIANCE.S(D7:D111,G7:G111)/_xlfn.VAR.S(G7:G111) -> 1.2421196
B9: 44263 | C9: 3129.3501 | D9: =C9/C8-1 -> -0.047700921 | F9: 15030.95 | G9: =F9/F8-1 -> 0.0062156893 | I9: Market Beta | J9: =J7+J10 -> 1
B10: 44270 | C10: 2960.3 | D10: =C10/C9-1 -> -0.054020817 | F10: 14744 | G10: =F10/F9-1 -> -0.019090622 | I10: Market Beta Weight | J10: 0.25 | M10: Beta 3 | N10: =N28 -> 1.2421196
B11: 44277 | C11: 2855.2 | D11: =C11/C10-1 -> -0.035503191 | F11: 14507.3 | G11: =F11/F10-1 -> -0.016054001 | M11: SUMMARY OUTPUT
B12: 44284 | C12: 2912.7 | D12: =C12/C11-1 -> 0.020138695 | F12: 14867.35 | G12: =F12/F11-1 -> 0.024818526 | I12: Adjusted Beta | J12: =(J6*J7)+(J9*J10) -> 1.1815897
B13: 44291 | C13: 2947.75 | D13: =C13/C12-1 -> 0.012033525 | F13: 14834.85 | G13: =F13/F12-1 -> -0.0021859982 | M13: Regression Statistics
B14: 44298 | C14: 2919.8999 | D14: =C14/C13-1 -> -0.0094479172 | F14: 14617.85 | G14: =F14/F13-1 -> -0.014627718 | M14: Multiple R | N14: 0.51108084
B15: 44305 | C15: 2713.7 | D15: =C15/C14-1 -> -0.070618842 | F15: 14341.35 | G15: =F15/F14-1 -> -0.018915231 | M15: R Square | N15: 0.26120363
B16: 44312 | C16: 2852.8999 | D16: =C16/C15-1 -> 0.051295262 | F16: 14631.1 | G16: =F16/F15-1 -> 0.020203817 | M16: Adjusted R Square | N16: 0.25396053
B17: 44319 | C17: 2895.5 | D17: =C17/C16-1 -> 0.014932209 | F17: 14823.15 | G17: =F17/F16-1 -> 0.013126203 | M17: Standard Error | N17: 0.042285169
B18: 44326 | C18: 2844.6499 | D18: =C18/C17-1 -> -0.017561768 | F18: 14677.8 | G18: =F18/F17-1 -> -0.0098056474 | M18: Observations | N18: 104
B19: 44333 | C19: 3034.1499 | D19: =C19/C18-1 -> 0.066616282 | F19: 15175.3 | G19: =F19/F18-1 -> 0.033894726
B20: 44340 | C20: 3022.1001 | D20: =C20/C19-1 -> -0.0039713938 | F20: 15435.65 | G20: =F20/F19-1 -> 0.017156207 | M20: ANOVA
B21: 44347 | C21: 3197 | D21: =C21/C20-1 -> 0.05787363 | F21: 15670.25 | G21: =F21/F20-1 -> 0.015198557 | N21: df | O21: SS | P21: MS | Q21: F | R21: Significance F
B22: 44354 | C22: 3175.55 | D22: =C22/C21-1 -> -0.0067093997 | F22: 15799.35 | G22: =F22/F21-1 -> 0.0082385162 | M22: Regression | N22: 1 | O22: 0.064480852 | P22: 0.064480852 | Q22: 36.0624 | R22: 2.9630302e-08
B23: 44361 | C23: 3317.7 | D23: =C23/C22-1 -> 0.044763868 | F23: 15683.35 | G23: =F23/F22-1 -> -0.0073420744 | M23: Residual | N23: 102 | O23: 0.18237962 | P23: 0.0017880355
B24: 44368 | C24: 3315.3501 | D24: =C24/C23-1 -> -0.00070827773 | F24: 15860.35 | G24: =F24/F23-1 -> 0.011285854 | M24: Total | N24: 103 | O24: 0.24686047
B25: 44375 | C25: 3314.3 | D25: =C25/C24-1 -> -0.00031672341 | F25: 15722.2 | G25: =F25/F24-1 -> -0.0087103637
B26: 44382 | C26: 3377.6001 | D26: =C26/C25-1 -> 0.01909907 | F26: 15689.8 | G26: =F26/F25-1 -> -0.0020608051 | N26: Coefficients | O26: Standard Error | P26: t Stat | Q26: P-value | R26: Lower 95% | S26: Upper 95% | T26: Lower 95.0% | U26: Upper 95.0%
B27: 44389 | C27: 3349.2 | D27: =C27/C26-1 -> -0.0084083806 | F27: 15923.4 | G27: =F27/F26-1 -> 0.014888691 | M27: Intercept | N27: 0.00010669116 | O27: 0.0041708465 | P27: 0.025580217 | Q27: 0.97964214 | R27: -0.008166163 | S27: 0.0083795453 | T27: -0.008166163 | U27: 0.0083795453
B28: 44396 | C28: 3413.2 | D28: =C28/C27-1 -> 0.019109041 | F28: 15856.05 | G28: =F28/F27-1 -> -0.004229661 | M28: X Variable 1 | N28: 1.2421196 | O28: 0.20684075 | P28: 6.0051978 | Q28: 2.9630302e-08 | R28: 0.83185198 | S28: 1.6523873 | T28: 0.83185198 | U28: 1.6523873
B29: 44403 | C29: 3500.8 | D29: =C29/C28-1 -> 0.025665094 | F29: 15763.05 | G29: =F29/F28-1 -> -0.0058652692
B30: 44410 | C30: 3529.2 | D30: =C30/C29-1 -> 0.0081124033 | F30: 16238.2 | G30: =F30/F29-1 -> 0.030143303
B31: 44417 | C31: 3594.55 | D31: =C31/C30-1 -> 0.018516972 | F31: 16529.1 | G31: =F31/F30-1 -> 0.017914511
B32: 44424 | C32: 3643.1001 | D32: =C32/C31-1 -> 0.013506572 | F32: 16450.5 | G32: =F32/F31-1 -> -0.0047552263
B33: 44431 | C33: 3833.05 | D33: =C33/C32-1 -> 0.052139646 | F33: 16705.199 | G33: =F33/F32-1 -> 0.015482765
B34: 44438 | C34: 3938.8999 | D34: =C34/C33-1 -> 0.027615046 | F34: 17323.6 | G34: =F34/F33-1 -> 0.037018439
B35: 44445 | C35: 3950.5 | D35: =C35/C34-1 -> 0.0029450096 | F35: 17369.25 | G35: =F35/F34-1 -> 0.0026351562
B36: 44452 | C36: 4239.6499 | D36: =C36/C35-1 -> 0.073193242 | F36: 17585.15 | G36: =F36/F35-1 -> 0.012430035
B37: 44459 | C37: 4422.3501 | D37: =C37/C36-1 -> 0.043093227 | F37: 17853.199 | G37: =F37/F36-1 -> 0.015242908
B38: 44466 | C38: 4235.6001 | D38: =C38/C37-1 -> -0.042228678 | F38: 17532.051 | G38: =F38/F37-1 -> -0.017988285
B39: 44473 | C39: 4407.9502 | D39: =C39/C38-1 -> 0.040690833 | F39: 17895.199 | G39: =F39/F38-1 -> 0.020713403
B40: 44480 | C40: 5323.75 | D40: =C40/C39-1 -> 0.20776092 | F40: 18338.551 | G40: =F40/F39-1 -> 0.024774888
... B111: 44977 | C111: 3552.8501 | D111: =C111/C110-1 -> 0.0022144141 | F111: 17844.6 | G111: =F111/F110-1 -> -0.0055505185

Sheet Raw FS
B2: Particulars | C2: 42795 | D2: 43160 | E2: 43525 | F2: 43891 | G2: 44256 | H2: 44621 | I2: 44986 | J2: 45352 | K2: 45717 | L2: 46082
B4: Equity Capital | C4: 240 | D4: 240 | E4: 240 | F4: 240 | G4: 240 | H4: 240 | I4: 240 | J4: 240 | K4: 240 | L4: 240
B5: Reserves | C5: 36400 | D5: 38074 | E5: 41169 | F5: 45025 | G5: 46223 | H5: 47771 | I5: 55755 | J5: 63427 | K5: 71978 | L5: 83330
B6: Borrowings -
B7: Long term Borrowings | C7: 1436 | D7: 1772 | E7: 1523 | F7: 2029 | G7: 655 | H7: 230 | I7: 0 | J7: 1 | K7: 3 | L7: 31
B8: Short term Borrowings | C8: 6655 | D8: 7980 | E8: 8371 | F8: 5549 | G8: 2869 | H8: 701 | I8: 6198 | J8: 2844 | K8: 1867 | L8: 4050
B9: Lease Liabilities | C9: 0 | D9: 0 | E9: 0 | F9: 0 | G9: 345 | H9: 360 | I9: 688 | J9: 428 | K9: 493 | L9: 546
B10: Other Borrowings | C10: 1741 | D10: 633 | E10: 621 | F10: 737 | G10: 0 | H10: 0 | I10: 0 | J10: 0 | K10: 0 | L10: 0
B11: Other Liabilities -
B12: Non controlling int | C12: 3791 | D12: 3884 | E12: 3314 | F12: 3860 | G12: 3017 | H12: 3055 | I12: 3320 | J12: 3459 | K12: 268 | L12: 310
B13: Trade Payables | C13: 4395 | D13: 4766 | E13: 4148 | F13: 3584 | G13: 3974 | H13: 4490 | I13: 5682 | J13: 5653 | K13: 6184 | L13: 7334
B14: Advance from Customers | C14: 121 | D14: 30 | E14: 69 | F14: 53 | G14: 47 | H14: 29 | I14: 41 | J14: 43 | K14: 25 | L14: 137
B15: Other liability items | C15: 6317 | D15: 6918 | E15: 5135 | F15: 7118 | G15: 10253 | H15: 12901 | I15: 8788 | J15: 9232 | K15: 10851 | L15: 12429
B16: Total Liabilities | C16: 61095 | D16: 64297 | E16: 64590 | F16: 68194 | G16: 67622 | H16: 69776 | I16: 80712 | J16: 85328 | K16: 91908 | L16: 108407
B18: Fixed Assets -
B19: Land | C19: 475 | D19: 523 | E19: 651 | F19: 686 | G19: 642 | H19: 862 | I19: 898 | J19: 1047 | K19: 1017 | L19: 1190
B20: Building | C20: 4742 | D20: 4877 | E20: 5414 | F20: 5844 | G20: 5937 | H20: 6048 | I20: 6820 | J20: 6803 | K20: 7052 | L20: 8074
B21: Plant Machinery | C21: 7556 | D21: 8723 | E21: 9814 | F21: 10976 | G21: 11629 | H21: 12363 | I21: 13077 | J21: 13706 | K21: 14215 | L21: 15882
B22: Equipments | C22: 170 | D22: 195 | E22: 221 | F22: 233 | G22: 273 | H22: 305 | I22: 327 | J22: 345 | K22: 368 | L22: 418
B23: Furniture n fittings | C23: 349 | D23: 373 | E23: 400 | F23: 427 | G23: 421 | H23: 423 | I23: 444 | J23: 454 | K23: 481 | L23: 484
B24: Vehicles | C24: 107 | D24: 184 | E24: 246 | F24: 319 | G24: 371 | H24: 408 | I24: 447 | J24: 414 | K24: 478 | L24: 581
B25: Intangible Assets | C25: 5536 | D25: 11897 | E25: 14678 | F25: 16322 | G25: 15934 | H25: 6591 | I25: 8358 | J25: 8569 | K25: 8939 | L25: 9833
B26: Other fixed assets | C26: 5531 | D26: 175 | E26: 264 | F26: 310 | G26: 371 | H26: 11707 | I26: 12729 | J26: 12983 | K26: 13399 | L26: 23859
B27: Gross Block | C27: 24466 | D27: 26949 | E27: 31687 | F27: 35116 | G27: 35579 | H27: 38707 | I27: 43100 | J27: 44320 | K27: 45950 | L27: 60321
B28: Accumulated Depreciation | C28: 6791 | D28: 8096 | E28: 9850 | F28: 12269 | G28: 14026 | H28: 16042 | I28: 19035 | J28: 21072 | K28: 23363 | L28: 27499
B29: Net Block | C29: =C27-C28 -> 17675 | D29: =D27-D28 -> 18853 | E29: =E27-E28 -> 21837 | F29: =F27-F28 -> 22847 | G29: =G27-G28 -> 21553 | H29: =H27-H28 -> 22665 | I29: =I27-I28 -> 24065 | J29: =J27-J28 -> 23248 | ... L29: =L27-L28 -> 32822
B31: CWIP | C31: 2801 | D31: 2465 | E31: 1411 | F31: 1220 | G31: 1567 | H31: 1287 | I31: 4973 | J31: 5354 | K31: 6644 | L31: 3052
B32: Investments | C32: 1192 | D32: 7143 | E32: 7903 | F32: 10143 | G32: 9612 | H32: 12849 | I32: 14824 | J32: 15026 | K32: 18354 | L32: 24723
B34: Other Assets -
B35: Inventories | C35: 6833 | D35: 6881 | E35: 7886 | F35: 7875 | G35: 8997 | H35: 8925 | I35: 10513 | J35: 9868 | K35: 10243 | L35: 11493
B36: Trade receivables | C36: 7203 | D36: 7815 | E36: 8884 | F36: 9421 | G36: 9061 | H36: 10485 | I36: 11439 | J36: 11249 | K36: 13046 | L36: 15510
B37: Cash Equivalents | C37: 15141 | D37: 9929 | E37: 7276 | F37: 6488 | G37: 6446 | H37: 5033 | I37: 5770 | J37: 10521 | K37: 11332 | L37: 11603
B38: Loans n Advances | C38: 2160 | D38: 865 | E38: 855 | F38: 678 | G38: 649 | H38: 720 | I38: 818 | J38: 855 | K38: 785 | L38: 923
B39: Other asset items | C39: 8091 | D39: 10346 | E39: 8538 | F39: 9522 | G39: 9737 | H39: 7812 | I39: 8309 | J39: 9206 | K39: 8918 | L39: 8282
B40: Total Assets | C40: 61095 | D40: 64297 | E40: 64590 | F40: 68194 | G40: 67622 | H40: 69776 | I40: 80712 | J40: 85328 | K40: 91908 | L40: 108407

Sheet Data Room
B2: Calculation of ROIC | G2: ='Raw FS'!H$2 -> 44621 | H2: ='Raw FS'!I$2 -> 44986 | I2: ='Raw FS'!J$2 -> 45352 | J2: ='Raw FS'!K$2 -> 45717 | K2: ='Raw FS'!L$2 -> 46082
B4: Current Assets
B5: ='Raw FS'!B35 -> Inventories | G5: ='Raw FS'!H35 -> 8925 | H5: ='Raw FS'!I35 -> 10513 | I5: ='Raw FS'!J35 -> 9868 | J5: ='Raw FS'!K35 -> 10243 | K5: ='Raw FS'!L35 -> 11493
B6: ='Raw FS'!B36 -> Trade receivables | G6: ='Raw FS'!H36 -> 10485 | H6: ='Raw FS'!I36 -> 11439 | I6: ='Raw FS'!J36 -> 11249 | J6: ='Raw FS'!K36 -> 13046 | K6: ='Raw FS'!L36 -> 15510
B7: ='Raw FS'!B38 -> Loans n Advances | G7: ='Raw FS'!H38 -> 720 | H7: ='Raw FS'!I38 -> 818 | I7: ='Raw FS'!J38 -> 855 | J7: ='Raw FS'!K38 -> 785 | K7: ='Raw FS'!L38 -> 923
B8: ='Raw FS'!B39 -> Other asset items | G8: ='Raw FS'!H39 -> 7812 | H8: ='Raw FS'!I39 -> 8309 | I8: ='Raw FS'!J39 -> 9206 | J8: ='Raw FS'!K39 -> 8918 | K8: ='Raw FS'!L39 -> 8282
B9: Total Current Assets | G9: =SUM(G5:G8) -> 27942 | H9: =SUM(H5:H8) -> 31079 | I9: =SUM(I5:I8) -> 31178 | J9: =SUM(J5:J8) -> 32992 | K9: =SUM(K5:K8) -> 36208
B11: Current Liabilities
B12: ='Raw FS'!B13 -> Trade Payables | G12: ='Raw FS'!H13 -> 4490 | H12: ='Raw FS'!I13 -> 5682 | I12: ='Raw FS'!J13 -> 5653 | J12: ='Raw FS'!K13 -> 6184 | K12: ='Raw FS'!L13 -> 7334
B13: ='Raw FS'!B14 -> Advance from Customers | G13: ='Raw FS'!H14 -> 29 | H13: ='Raw FS'!I14 -> 41 | I13: ='Raw FS'!J14 -> 43 | J13: ='Raw FS'!K14 -> 25 | K13: ='Raw FS'!L14 -> 137
B14: ='Raw FS'!B15 -> Other liability items | G14: ='Raw FS'!H15 -> 12901 | H14: ='Raw FS'!I15 -> 8788 | I14: ='Raw FS'!J15 -> 9232 | J14: ='Raw FS'!K15 -> 10851 | K14: ='Raw FS'!L15 -> 12429
B15: Total Current Liabilities | G15: =SUM(G12:G14) -> 17420 | H15: =SUM(H12:H14) -> 14511 | I15: =SUM(I12:I14) -> 14928 | J15: =SUM(J12:J14) -> 17060 | K15: =SUM(K12:K14) -> 19900
A17: # | B17: Net Working Capital | G17: =G9-G15 -> 10522 | H17: =H9-H15 -> 16568 | I17: =I9-I15 -> 16250 | J17: =J9-J15 -> 15932 | K17: =K9-K15 -> 16308
B19: Non Current Assets
B20: ='Raw FS'!B19 -> Land | G20: ='Raw FS'!H19 -> 862 | H20: ='Raw FS'!I19 -> 898 | I20: ='Raw FS'!J19 -> 1047 | J20: ='Raw FS'!K19 -> 1017 | K20: ='Raw FS'!L19 -> 1190
B21: ='Raw FS'!B20 -> Building | G21: ='Raw FS'!H20 -> 6048 | H21: ='Raw FS'!I20 -> 6820 | I21: ='Raw FS'!J20 -> 6803 | J21: ='Raw FS'!K20 -> 7052 | K21: ='Raw FS'!L20 -> 8074
B22: ='Raw FS'!B21 -> Plant Machinery | G22: ='Raw FS'!H21 -> 12363 | H22: ='Raw FS'!I21 -> 13077 | I22: ='Raw FS'!J21 -> 13706 | J22: ='Raw FS'!K21 -> 14215 | K22: ='Raw FS'!L21 -> 15882
B23: ='Raw FS'!B22 -> Equipments | G23: ='Raw FS'!H22 -> 305 | H23: ='Raw FS'!I22 -> 327 | I23: ='Raw FS'!J22 -> 345 | J23: ='Raw FS'!K22 -> 368 | K23: ='Raw FS'!L22 -> 418
B24: ='Raw FS'!B23 -> Furniture n fittings | G24: ='Raw FS'!H23 -> 423 | H24: ='Raw FS'!I23 -> 444 | I24: ='Raw FS'!J23 -> 454 | J24: ='Raw FS'!K23 -> 481 | K24: ='Raw FS'!L23 -> 484
B25: ='Raw FS'!B24 -> Vehicles | G25: ='Raw FS'!H24 -> 408 | H25: ='Raw FS'!I24 -> 447 | I25: ='Raw FS'!J24 -> 414 | J25: ='Raw FS'!K24 -> 478 | K25: ='Raw FS'!L24 -> 581
B26: ='Raw FS'!B25 -> Intangible Assets | G26: ='Raw FS'!H25 -> 6591 | H26: ='Raw FS'!I25 -> 8358 | I26: ='Raw FS'!J25 -> 8569 | J26: ='Raw FS'!K25 -> 8939 | K26: ='Raw FS'!L25 -> 9833
B27: ='Raw FS'!B26 -> Other fixed assets | G27: ='Raw FS'!H26 -> 11707 | H27: ='Raw FS'!I26 -> 12729 | I27: ='Raw FS'!J26 -> 12983 | J27: ='Raw FS'!K26 -> 13399 | K27: ='Raw FS'!L26 -> 23859
B29: Gross Block | G29: =SUM(G20:G27) -> 38707 | H29: =SUM(H20:H27) -> 43100 | I29: =SUM(I20:I27) -> 44321 | J29: =SUM(J20:J27) -> 45949 | K29: =SUM(K20:K27) -> 60321
B30: Accumulated Dereciation | G30: =-'Raw FS'!H28 -> -16042 | H30: =-'Raw FS'!I28 -> -19035 | I30: =-'Raw FS'!J28 -> -21072 | J30: =-'Raw FS'!K28 -> -23363 | K30: =-'Raw FS'!L28 -> -27499
A31: # | B31: Net Non Current Assets | G31: =SUM(G29:G30) -> 22665 | H31: =SUM(H29:H30) -> 24065 | I31: =SUM(I29:I30) -> 23249 | J31: =SUM(J29:J30) -> 22586 | K31: =SUM(K29:K30) -> 32822
A33: # | B33: Inventory Capital | G33: =G17+G31 -> 33187 | H33: =H17+H31 -> 40633 | I33: =I17+I31 -> 39499 | J33: =J17+J31 -> 38518 | K33: =K17+K31 -> 49130
B34: EBIT | G34: =HistoricalFS!H29 -> 8113.83 | H34: =HistoricalFS!I29 -> 9121.01 | I34: =HistoricalFS!J29 -> 10461.13 | J34: =HistoricalFS!K29 -> 12539.07 | K34: =HistoricalFS!L29 -> 14793.55
A36: # | B36: ROIC | G36: =G34/G33 -> 0.2444882 | H36: =H34/H33 -> 0.22447297 | I36: =I34/I33 -> 0.26484544 | J36: =J34/J33 -> 0.32553793 | K36: =K34/K33 -> 0.30111032
A39: # | B39: Calculation of Reinvestment Rate | G39: ='Raw FS'!H$2 -> 44621 | H39: ='Raw FS'!I$2 -> 44986 | I39: ='Raw FS'!J$2 -> 45352 | J39: ='Raw FS'!K$2 -> 45717 | K39: ='Raw FS'!L$2 -> 46082
B41: Net CapEx | G41: =-SUM(HistoricalFS!H87:H88) -> 1434 | H41: =-SUM(HistoricalFS!I87:I88) -> 2065 | I41: =-SUM(HistoricalFS!J87:J88) -> 2171 | J41: =-SUM(HistoricalFS!K87:K88) -> 2068 | K41: =-SUM(HistoricalFS!L87:L88) -> 3513
B42: Change in Working Capital | H42: =H17-G17 -> 6046 | I42: =I17-H17 -> -318 | J42: =J17-I17 -> -318 | K42: =K17-J17 -> 376
B44: EBIT | G44: =G34 -> 8113.83 | H44: =H34 -> 9121.01 | I44: =I34 -> 10461.13 | J44: =J34 -> 12539.07 | K44: =K34 -> 14793.55
B45: Marginal Tax Rate | G45: 0.25 | H45: 0.25 | I45: 0.25 | J45: 0.25 | K45: 0.25
B46: EBIT (1-T) | G46: =G44*(1-G45) -> 6085.3725 | H46: =H44*(1-H45) -> 6840.7575 | I46: =I44*(1-I45) -> 7845.8475 | J46: =J44*(1-J45) -> 9404.3025 | K46: =K44*(1-K45) -> 11095.163
B48: Reinvestment | H48: =SUM(H41:H42) -> 8111 | I48: =SUM(I41:I42) -> 1853 | J48: =SUM(J41:J42) -> 1750 | K48: =SUM(K41:K42) -> 3889
B50: Reinvestment Rate | H50: =H48/H46 -> 1.1856874 | I50: =I48/I46 -> 0.23617589 | J50: =J48/J46 -> 0.18608504 | K50: =K48/K46 -> 0.35051312
J52: 4 Year Average | K52: =AVERAGE(H50:K50) -> 0.48961536
J53: 4 Year Median | K53: =MEDIAN(H50:K50) -> 0.2933445
A55: # | B55: Calculation of Growth Rate | G55: ='Raw FS'!H$2 -> 44621 | H55: ='Raw FS'!I$2 -> 44986 | I55: ='Raw FS'!J$2 -> 45352 | J55: ='Raw FS'!K$2 -> 45717 | K55: ='Raw FS'!L$2 -> 46082
B57: Reinvestment Rate | H57: =H50 -> 1.1856874 | I57: =I50 -> 0.23617589 | J57: =J50 -> 0.18608504 | K57: =K50 -> 0.35051312
B58: ROIC | H58: =H36 -> 0.22447297 | I58: =I36 -> 0.26484544 | J58: =J36 -> 0.32553793 | K58: =K36 -> 0.30111032
B60: Intrinsic Growth | H60: =H58*H57 -> 0.26615477 | I60: =I58*I57 -> 0.062550107 | J60: =J58*J57 -> 0.060577739 | K60: =K58*K57 -> 0.10554312
J62: 4 Year Average | K62: =AVERAGE(H60:K60) -> 0.12370643
J63: 4 Year Median | K63: =MEDIAN(H60:K60) -> 0.084046612

Sheet DCF
A2: # | B2: Calculation of PV of FCFF | D2: ='Data Room'!K2 -> 46082 | E2: =D2+366 -> 46448 | F2: =E2+366 -> 46814 | G2: =F2+366 -> 47180 | H2: =G2+366 -> 47546 | I2: =H2+366 -> 47912
B4: EBIT | D4: =HistoricalFS!L29 -> 14793.55
B6: Tax Rate | D6: 0.25 | E6: =D6 -> 0.25 | F6: =E6 -> 0.25 | G6: =F6 -> 0.25 | H6: =G6 -> 0.25 | I6: =H6 -> 0.25
B8: EBIT(1-T) | D8: =D4*(1-D6) -> 11095.163 | E8: =E4*(1-E6) -> 0 | F8: =F4*(1-F6) -> 0 | G8: =G4*(1-G6) -> 0 | H8: =H4*(1-H6) -> 0 | I8: =I4*(1-I6) -> 0
B10: Less: Reinvestment rate | D10: ='Data Room'!K53 -> 0.2933445 | E10: =D10+(($I$10-$D$10)/4) -> 0.29750838 | F10: =E10+(($I$10-$D$10)/4) -> 0.30167225 | G10: =F10+(($I$10-$D$10)/4) -> 0.30583613 | H10: =G10+(($I$10-$D$10)/4) -> 0.31 | I10: 0.31
B12: Free Cash Flows to the Firm (FCFF) | D12: =D8*(1-D10) -> 7840.4576 | E12: =E8*(1-E10) -> 0 | F12: =F8*(1-F10) -> 0 | G12: =G8*(1-G10) -> 0 | H12: =H8*(1-H10) -> 0 | I12: =I8*(1-I10) -> 0
B14: Mid Year Convention
B15: Discounting Factor
B17: PV of PCFF
B19: Expected Growth
B20: Terminal Growth
B21: WACC
